[{"_tast_name": "org.apache.mahout.common.intpairwritabletest@testcomparable", "_outcome": "pass"}, {"_tast_name": "org.apache.mahout.math.testvectorview@testsize", "_outcome": "pass"}, {"_tast_name": "org.apache.mahout.ga.watchmaker.cd.tool.toolcombinertest@testcreatedescriptionignored", "_outcome": "pass"}, {"_tast_name": "org.apache.mahout.cf.taste.impl.common.fastbyidmaptest@testgrow", "_outcome": "pass"}, {"_tast_name": "org.apache.mahout.cf.taste.impl.model.genericitempreferencearraytest@testsortvalue", "_outcome": "pass"}, {"_tast_name": "org.apache.mahout.clustering.testclusterinterface@testcanopyasformatstringsparsewithbindings", "_outcome": "pass"}, {"_tast_name": "org.apache.mahout.math.hadoop.testdistributedrowmatrix@testmatrixtimessquaredvector", "_outcome": "error"}, {"_tast_name": "org.apache.mahout.cf.taste.impl.model.booleanitempreferencearraytest@testsetvalue", "_outcome": "pass"}, {"_tast_name": "org.apache.mahout.cf.taste.impl.common.refreshhelpertest@testdependencies", "_outcome": "pass"}, {"_tast_name": "org.apache.mahout.clustering.testclusterclassifier@testmscanopyclassification", "_outcome": "pass"}, {"_tast_name": "org.apache.mahout.math.testsequentialaccesssparsevector@testdot2", "_outcome": "pass"}, {"_tast_name": "org.apache.mahout.clustering.testclusterclassifier@testsoftclusterclassification", "_outcome": "pass"}, {"_tast_name": "org.apache.mahout.math.jet.random.negativebinomialtest@testdistributionfunctions", "_outcome": "pass"}, {"_tast_name": "org.apache.mahout.cf.taste.impl.recommender.topitemstest@testtopuseruser", "_outcome": "pass"}, {"_tast_name": "org.apache.mahout.cf.taste.impl.similarity.spearmancorrelationsimilaritytest@testsimple", "_outcome": "pass"}, {"_tast_name": "org.apache.mahout.clustering.kmeans.testrandomseedgenerator@testrandomseedgenerator", "_outcome": "pass"}, {"_tast_name": "org.apache.mahout.vectorizer.collocations.llr.gramtest@testhashing", "_outcome": "pass"}, {"_tast_name": "org.apache.mahout.clustering.topdown.postprocessor.clustercountreadertest@testgetnumberofclusters", "_outcome": "pass"}, {"_tast_name": "org.apache.mahout.classifier.bayes.bayesfeaturemapreducetest@testnofilters", "_outcome": "error"}, {"_tast_name": "org.apache.mahout.math.hadoop.stochasticsvd.uppertriangulartest@testbasics", "_outcome": "pass"}, {"_tast_name": "org.apache.mahout.fpm.pfpgrowth.pfpgrowthretaildatatest@testretaildataminsup100insteps", "_outcome": "error"}, {"_tast_name": "org.apache.mahout.common.distance.testmahalanobisdistancemeasure@testmeasure", "_outcome": "pass"}, {"_tast_name": "org.apache.mahout.cf.taste.impl.common.fastmaptest@testnull2", "_outcome": "pass"}, {"_tast_name": "org.apache.mahout.cf.taste.impl.common.runningaveragetest@testfull", "_outcome": "pass"}, {"_tast_name": "org.apache.mahout.cf.taste.impl.model.file.filedatamodeltest@testnumuserspreferring", "_outcome": "pass"}, {"_tast_name": "org.apache.mahout.vectorizer.sparsevectorsfromsequencefilestest@testcreatetermfrequencyvectors", "_outcome": "error"}, {"_tast_name": "org.apache.mahout.classifier.bayes.cbayesclassifiertest@test", "_outcome": "pass"}, {"_tast_name": "org.apache.mahout.math.hadoop.similarity.cooccurrence.measures.vectorsimilaritymeasurestest@testcooccurrencecountsimilarity", "_outcome": "pass"}, {"_tast_name": "org.apache.mahout.clustering.testclusterinterface@testclusterasformatstring", "_outcome": "pass"}, {"_tast_name": "org.apache.mahout.classifier.discriminative.winnowtrainertest@testupdate", "_outcome": "pass"}, {"_tast_name": "org.apache.mahout.classifier.sgd.csvrecordfactorytest@testaddtovector", "_outcome": "pass"}, {"_tast_name": "org.apache.mahout.math.hadoop.stochasticsvd.localssvdsolverdensetest@testssvdsolverpoweriterations1", "_outcome": "error"}, {"_tast_name": "org.apache.mahout.cf.taste.impl.recommender.treeclusteringrecommendertest@testrescorer", "_outcome": "pass"}, {"_tast_name": "org.apache.mahout.classifier.sgd.modeldissectortest@testcategoryordering", "_outcome": "pass"}, {"_tast_name": "org.apache.mahout.math.ssvd.sequentialoutofcoresvdtest@testrightvectors", "_outcome": "pass"}, {"_tast_name": "org.apache.mahout.clustering.dirichlet.testdistributions@testdnorm2", "_outcome": "pass"}, {"_tast_name": "org.apache.mahout.math.testvectorview@testviewpartover", "_outcome": "pass"}, {"_tast_name": "org.apache.mahout.clustering.dirichlet.testdistributions@testdnorm1", "_outcome": "pass"}, {"_tast_name": "org.apache.mahout.cf.taste.impl.neighborhood.thresholdneighborhoodtest@testneighborhood", "_outcome": "pass"}, {"_tast_name": "org.apache.mahout.clustering.lda.testmapreduce@testmapper", "_outcome": "pass"}, {"_tast_name": "org.apache.mahout.cf.taste.impl.recommender.treeclusteringrecommendertest@testhowmany", "_outcome": "pass"}, {"_tast_name": "org.apache.mahout.ga.watchmaker.cd.tool.toolreducertest@testcreatedescriptionnumerical", "_outcome": "pass"}, {"_tast_name": "org.apache.mahout.clustering.testclusterinterface@testclusterasformatstringsparse", "_outcome": "pass"}, {"_tast_name": "org.apache.mahout.cf.taste.impl.model.booleanuserpreferencearraytest@testsetvalue", "_outcome": "pass"}, {"_tast_name": "org.apache.mahout.math.vectortest@testaggregation", "_outcome": "pass"}, {"_tast_name": "org.apache.mahout.cf.taste.impl.common.invertedrunningaveragetest@testunsupported1", "_outcome": "pass"}, {"_tast_name": "org.apache.mahout.math.testvectorview@testassignvector", "_outcome": "pass"}, {"_tast_name": "org.apache.mahout.cf.taste.impl.common.invertedrunningaveragetest@testunsupported3", "_outcome": "pass"}, {"_tast_name": "org.apache.mahout.cf.taste.impl.common.invertedrunningaveragetest@testunsupported2", "_outcome": "pass"}, {"_tast_name": "org.apache.mahout.cf.taste.impl.recommender.knn.knnitembasedrecommendertest@testrecommender", "_outcome": "pass"}, {"_tast_name": "org.apache.mahout.clustering.testclusterclassifier@testcanopyclassification", "_outcome": "pass"}, {"_tast_name": "org.apache.mahout.math.vectorwritabletest@testrandomaccesssparsevectorwritable", "_outcome": "pass"}, {"_tast_name": "org.apache.mahout.cf.taste.hadoop.item.recommenderjobtest@testitemidindexreducer", "_outcome": "pass"}, {"_tast_name": "org.apache.mahout.clustering.meanshift.testmeanshift@testcanopymappereuclidean", "_outcome": "pass"}, {"_tast_name": "org.apache.mahout.cf.taste.impl.transforms.inverseuserfrequencytest@testiuf", "_outcome": "pass"}, {"_tast_name": "org.apache.mahout.cf.taste.impl.model.file.filedatamodeltest@testpreferencesforitem", "_outcome": "pass"}, {"_tast_name": "org.apache.mahout.cf.taste.impl.recommender.slopeone.slopeonerecommendertest@testdiffstdevbehavior", "_outcome": "pass"}, {"_tast_name": "org.apache.mahout.classifier.bayes.bayesclassifiertest@testresults", "_outcome": "pass"}, {"_tast_name": "org.apache.mahout.classifier.bayes.bayesfileformattertest@testcollapse", "_outcome": "pass"}, {"_tast_name": "org.apache.mahout.cf.taste.impl.model.booleanuserpreferencearraytest@testclone", "_outcome": "pass"}, {"_tast_name": "org.apache.mahout.math.testsingularvaluedecomposition@testmatricesvalues1", "_outcome": "pass"}, {"_tast_name": "org.apache.mahout.math.testvectorview@testplusvector", "_outcome": "pass"}, {"_tast_name": "org.apache.mahout.math.testvectorview@testcrossproduct", "_outcome": "pass"}, {"_tast_name": "org.apache.mahout.classifier.df.data.descriptorutilstest@testgeneratedescription", "_outcome": "pass"}, {"_tast_name": "org.apache.mahout.cf.taste.impl.model.memoryidmigratortest@teststore", "_outcome": "pass"}, {"_tast_name": "org.apache.mahout.ga.watchmaker.cd.tool.descriptionutilstest@testcreatenumericaldescription", "_outcome": "pass"}, {"_tast_name": "org.apache.mahout.clustering.canopy.testcanopycreation@testcanopygenmanhattanmr", "_outcome": "error"}, {"_tast_name": "org.apache.mahout.cf.taste.impl.model.genericitempreferencearraytest@testuserid", "_outcome": "pass"}, {"_tast_name": "org.apache.mahout.math.testmatrixview@testlikeintint", "_outcome": "pass"}, {"_tast_name": "org.apache.mahout.vectorizer.encoders.constantvalueencodertest@testasstring", "_outcome": "pass"}, {"_tast_name": "org.apache.mahout.ga.watchmaker.cd.tool.descriptionutilstest@testcreatenominaldescription", "_outcome": "pass"}, {"_tast_name": "org.apache.mahout.cf.taste.impl.model.file.fileidmigratortest@testloadfromfile", "_outcome": "pass"}, {"_tast_name": "org.apache.mahout.math.vectortest@testsparsevectorsparseiteration", "_outcome": "pass"}, {"_tast_name": "org.apache.mahout.clustering.spectral.common.testaffinitymatrixinputjob@testaffinitymatrixinputmapper", "_outcome": "pass"}, {"_tast_name": "org.apache.mahout.cf.taste.impl.similarity.euclideandistancesimilaritytest@testsimpleitemweighted", "_outcome": "pass"}, {"_tast_name": "org.apache.mahout.vectorizer.encoders.wordlikevalueencodertest@testdynamicweights", "_outcome": "pass"}, {"_tast_name": "org.apache.mahout.classifier.df.data.dataloadertest@testloaddatawithdescriptor", "_outcome": "pass"}, {"_tast_name": "org.apache.mahout.classifier.discriminative.linearmodeltest@testtimesdelta", "_outcome": "pass"}, {"_tast_name": "org.apache.mahout.cf.taste.impl.similarity.euclideandistancesimilaritytest@testnocorrelation1weighted", "_outcome": "pass"}, {"_tast_name": "org.apache.mahout.cf.taste.impl.similarity.loglikelihoodsimilaritytest@testnosimilarity", "_outcome": "pass"}, {"_tast_name": "org.apache.mahout.math.varinttest@testunsignedsize", "_outcome": "pass"}, {"_tast_name": "org.apache.mahout.math.hadoop.stochasticsvd.localssvdsolversparsesequentialtest@testssvdsolverpoweriterations1", "_outcome": "error"}, {"_tast_name": "org.apache.mahout.math.hadoop.stochasticsvd.ssvdprototypetest@testssvdprototype", "_outcome": "pass"}, {"_tast_name": "org.apache.mahout.vectorizer.encoders.wordlikevalueencodertest@testaddtovector", "_outcome": "pass"}, {"_tast_name": "org.apache.mahout.math.decomposer.lanczos.testlanczossolver@testlanczossolver", "_outcome": "failure"}, {"_tast_name": "org.apache.mahout.classifier.df.node.nodetest@testreadtree", "_outcome": "pass"}, {"_tast_name": "org.apache.mahout.cf.taste.impl.transforms.zscoretest@testonepref", "_outcome": "pass"}, {"_tast_name": "org.apache.mahout.cf.taste.impl.similarity.euclideandistancesimilaritytest@testsimpleitem", "_outcome": "pass"}, {"_tast_name": "org.apache.mahout.common.abstractjobtest@testflag", "_outcome": "pass"}, {"_tast_name": "org.apache.mahout.ga.watchmaker.cd.tool.descriptionutilstest@testextractnominalvalues", "_outcome": "pass"}, {"_tast_name": "org.apache.mahout.clustering.dirichlet.testmapreduce@testmapper", "_outcome": "pass"}, {"_tast_name": "org.apache.mahout.math.varinttest@testsignednegativelong", "_outcome": "pass"}, {"_tast_name": "org.apache.mahout.math.stats.entropy.informationgaintest@testinformationgain", "_outcome": "error"}, {"_tast_name": "org.apache.mahout.cf.taste.impl.common.invertedrunningaveragetest@testandstddevunsupported2", "_outcome": "pass"}, {"_tast_name": "org.apache.mahout.classifier.naivebayes.standardnaivebayesclassifiertest@testnaivebayes", "_outcome": "pass"}, {"_tast_name": "org.apache.mahout.cf.taste.impl.common.invertedrunningaveragetest@testaverageandstddev", "_outcome": "pass"}, {"_tast_name": "org.apache.mahout.math.vectortest@testiterator", "_outcome": "pass"}, {"_tast_name": "org.apache.mahout.math.jet.random.exponentialtest@testsetstate", "_outcome": "pass"}, {"_tast_name": "org.apache.mahout.math.vectortest@testhashcode", "_outcome": "pass"}, {"_tast_name": "org.apache.mahout.cf.taste.hadoop.similarity.item.itemsimilarityjobtest@testmaxsimilaritiesperitem", "_outcome": "error"}, {"_tast_name": "org.apache.mahout.math.testvectorview@testassigndouble", "_outcome": "pass"}, {"_tast_name": "org.apache.mahout.math.testmatrixview@testviewpartindexunder", "_outcome": "pass"}, {"_tast_name": "org.apache.mahout.math.testmatrixview@testviewrowindexunder", "_outcome": "pass"}, {"_tast_name": "org.apache.mahout.clustering.dirichlet.testdistributions@testrmultinom2", "_outcome": "pass"}, {"_tast_name": "org.apache.mahout.clustering.dirichlet.testdistributions@testrmultinom1", "_outcome": "pass"}, {"_tast_name": "org.apache.mahout.vectorizer.collocations.llr.gramkeytest@testwritable", "_outcome": "pass"}, {"_tast_name": "org.apache.mahout.fpm.pfpgrowth.fpgrowthtest@testmaxheapfpgrowthdata1", "_outcome": "pass"}, {"_tast_name": "org.apache.mahout.clustering.fuzzykmeans.testfuzzykmeansclustering@testfuzzykmeansseqjob", "_outcome": "pass"}, {"_tast_name": "org.apache.mahout.fpm.pfpgrowth.fpgrowthtest@testmaxheapfpgrowthdata2", "_outcome": "pass"}, {"_tast_name": "org.apache.mahout.cf.taste.impl.similarity.euclideandistancesimilaritytest@testnocorrelation3", "_outcome": "pass"}, {"_tast_name": "org.apache.mahout.cf.taste.impl.similarity.euclideandistancesimilaritytest@testnocorrelation2", "_outcome": "pass"}, {"_tast_name": "org.apache.mahout.cf.taste.impl.similarity.euclideandistancesimilaritytest@testnocorrelation1", "_outcome": "pass"}, {"_tast_name": "org.apache.mahout.classifier.bayes.bayesclassifierselftest@testselftestbayes", "_outcome": "error"}, {"_tast_name": "org.apache.mahout.cf.taste.impl.common.fastmaptest@testsizeempty", "_outcome": "pass"}, {"_tast_name": "org.apache.mahout.cf.taste.impl.recommender.genericuserbasedrecommendertest@testestimatepref", "_outcome": "pass"}, {"_tast_name": "org.apache.mahout.math.testvectorview@testget", "_outcome": "pass"}, {"_tast_name": "org.apache.mahout.math.pivotedmatrixtest@testswap", "_outcome": "pass"}, {"_tast_name": "org.apache.mahout.ga.watchmaker.cd.hadoop.cdmahoutevaluatortest@testevaluate", "_outcome": "error"}, {"_tast_name": "org.apache.mahout.cf.taste.impl.recommender.slopeone.memorydiffstoragetest@testgetdiff", "_outcome": "pass"}, {"_tast_name": "org.apache.mahout.math.testvectorview@testplusvectorcardinality", "_outcome": "pass"}, {"_tast_name": "org.apache.mahout.cf.taste.impl.model.memoryidmigratortest@testinitialize", "_outcome": "pass"}, {"_tast_name": "org.apache.mahout.cf.taste.impl.common.fastmaptest@testversushashmap", "_outcome": "pass"}, {"_tast_name": "org.apache.mahout.classifier.df.data.datasettest@testwritable", "_outcome": "pass"}, {"_tast_name": "org.apache.mahout.cf.taste.impl.model.genericuserpreferencearraytest@testhaspref", "_outcome": "pass"}, {"_tast_name": "org.apache.mahout.classifier.df.tools.visualizertest@testforestvisualize", "_outcome": "failure"}, {"_tast_name": "org.apache.mahout.clustering.meanshift.testmeanshift@testcanopyeuclideanmrjob", "_outcome": "error"}, {"_tast_name": "org.apache.mahout.math.testmatrixview@testdivide", "_outcome": "pass"}, {"_tast_name": "org.apache.mahout.cf.taste.impl.common.fastbyidmaptest@testclear", "_outcome": "pass"}, {"_tast_name": "org.apache.mahout.clustering.spectral.eigencuts.testeigencutsaffinitycutsjob@testeigencutsaffinitycutsmapper", "_outcome": "pass"}, {"_tast_name": "org.apache.mahout.math.jet.random.exponentialtest@testtostring", "_outcome": "pass"}, {"_tast_name": "org.apache.mahout.math.testdensevector@testsize", "_outcome": "pass"}, {"_tast_name": "org.apache.mahout.fpm.pfpgrowth.fpgrowthtest@testnonullpointerexceptionwhenreturnablefeaturesisnull", "_outcome": "pass"}, {"_tast_name": "org.apache.mahout.clustering.canopy.testcanopycreation@testreferenceeuclidean", "_outcome": "pass"}, {"_tast_name": "org.apache.mahout.cf.taste.impl.common.weightedrunningaveragetest@testweightedandstddev", "_outcome": "pass"}, {"_tast_name": "org.apache.mahout.math.testvectorview@testviewpartcardinality", "_outcome": "pass"}, {"_tast_name": "org.apache.mahout.math.testvectorview@testnormalize", "_outcome": "pass"}, {"_tast_name": "org.apache.mahout.cf.taste.impl.model.booleanitempreferencearraytest@testitemid", "_outcome": "pass"}, {"_tast_name": "org.apache.mahout.math.stats.loglikelihoodtest@testloglikelihood", "_outcome": "pass"}, {"_tast_name": "org.apache.mahout.cf.taste.hadoop.item.recommenderjobtest@testitemfilterasvectorandprefsreducer", "_outcome": "pass"}, {"_tast_name": "org.apache.mahout.math.testsingularvaluedecomposition@testmorecolumns", "_outcome": "pass"}, {"_tast_name": "org.apache.mahout.cf.taste.impl.common.fastmaptest@testkeyset", "_outcome": "pass"}, {"_tast_name": "org.apache.mahout.fpm.pfpgrowth.pfpgrowthtest@teststartparallelfpgrowth", "_outcome": "error"}, {"_tast_name": "org.apache.mahout.clustering.dirichlet.testmapreduce@testdrivermnriterations", "_outcome": "error"}, {"_tast_name": "org.apache.mahout.fpm.pfpgrowth.fpgrowthtest@testmaxheapfpgrowth", "_outcome": "pass"}, {"_tast_name": "org.apache.mahout.math.testvectorview@testassignbinaryfunction3", "_outcome": "pass"}, {"_tast_name": "org.apache.mahout.cf.taste.hadoop.item.recommenderjobtest@testtoitemprefsmapper", "_outcome": "pass"}, {"_tast_name": "org.apache.mahout.cf.taste.impl.recommender.topitemstest@testtopuseruseralt", "_outcome": "pass"}, {"_tast_name": "org.apache.mahout.classifier.sequencelearning.hmm.hmmevaluatortest@testmodellikelihood", "_outcome": "pass"}, {"_tast_name": "org.apache.mahout.clustering.testgaussianaccumulators@testaccumulatorweightedresults2", "_outcome": "pass"}, {"_tast_name": "org.apache.mahout.math.hadoop.stats.basicstatstest@teststddevforgivenmean", "_outcome": "error"}, {"_tast_name": "org.apache.mahout.cf.taste.impl.similarity.pearsoncorrelationsimilaritytest@testfullitemcorrelation1", "_outcome": "pass"}, {"_tast_name": "org.apache.mahout.cf.taste.impl.similarity.pearsoncorrelationsimilaritytest@testfullitemcorrelation2", "_outcome": "pass"}, {"_tast_name": "org.apache.mahout.math.ssvd.sequentialbigsvdtest@testleftvectors", "_outcome": "pass"}, {"_tast_name": "org.apache.mahout.cf.taste.hadoop.item.recommenderjobtest@testtovectorandprefreducer", "_outcome": "pass"}, {"_tast_name": "org.apache.mahout.clustering.dirichlet.testdistributions@testdnorm", "_outcome": "pass"}, {"_tast_name": "org.apache.mahout.math.testmatrixview@testassignmatrixbinaryfunction", "_outcome": "pass"}, {"_tast_name": "org.apache.mahout.cf.taste.hadoop.item.recommenderjobtest@testpartialmultiplymapper", "_outcome": "pass"}, {"_tast_name": "org.apache.mahout.cf.taste.impl.recommender.slopeone.memorydiffstoragetest@testadd", "_outcome": "pass"}, {"_tast_name": "org.apache.mahout.math.hadoop.testdistributedrowmatrix@testmatrixtimesmatrix", "_outcome": "error"}, {"_tast_name": "org.apache.mahout.vectorizer.dictionaryvectorizertest@testcreatetermfrequencyvectorsseq", "_outcome": "error"}, {"_tast_name": "org.apache.mahout.cf.taste.impl.similarity.file.fileitemsimilaritytest@testloadfromfile", "_outcome": "pass"}, {"_tast_name": "org.apache.mahout.math.testmatrixview@testassignmatrixbinaryfunctioncardinality", "_outcome": "pass"}, {"_tast_name": "org.apache.mahout.math.stats.entropy.entropytest@testyn", "_outcome": "error"}, {"_tast_name": "org.apache.mahout.clustering.testclusterclassifier@testclusteriteratorkmeans", "_outcome": "pass"}, {"_tast_name": "org.apache.mahout.classifier.sequencelearning.hmm.hmmtrainertest@testscaledbaumwelchtraining", "_outcome": "pass"}, {"_tast_name": "org.apache.mahout.cf.taste.impl.recommender.slopeone.slopeonerecommendertest@testbestrating", "_outcome": "pass"}, {"_tast_name": "org.apache.mahout.math.stats.loglikelihoodtest@testrootnegativellr", "_outcome": "pass"}, {"_tast_name": "org.apache.mahout.cf.taste.impl.model.memoryidmigratortest@testtolong", "_outcome": "pass"}, {"_tast_name": "org.apache.mahout.classifier.evaluation.auctest@testauc", "_outcome": "pass"}, {"_tast_name": "org.apache.mahout.clustering.kmeans.testkmeansclustering@testkmeanscombiner", "_outcome": "pass"}, {"_tast_name": "org.apache.mahout.classifier.bayes.cbayesclassifiertest@testresults", "_outcome": "pass"}, {"_tast_name": "org.apache.mahout.fpm.pfpgrowth.pfpgrowthtest@teststartparallelfpgrowthinsteps", "_outcome": "error"}, {"_tast_name": "org.apache.mahout.cf.taste.impl.model.genericitempreferencearraytest@testsort", "_outcome": "pass"}, {"_tast_name": "org.apache.mahout.cf.taste.impl.eval.genericrecommenderirstatsevaluatorimpltest@testevaluate", "_outcome": "pass"}, {"_tast_name": "org.apache.mahout.clustering.spectral.eigencuts.testeigencutsaffinitycutsjob@testeigencutsaffinitycutscombiner", "_outcome": "pass"}, {"_tast_name": "org.apache.mahout.classifier.df.data.descriptorutilstest@testparsedescriptor", "_outcome": "pass"}, {"_tast_name": "org.apache.mahout.math.matrixwritabletest@testsparsematrixwritable", "_outcome": "pass"}, {"_tast_name": "org.apache.mahout.ga.watchmaker.cd.hadoop.datasetsplittest@teststorejobparameters", "_outcome": "pass"}, {"_tast_name": "org.apache.mahout.cf.taste.impl.common.fastmaptest@testnull1", "_outcome": "pass"}, {"_tast_name": "org.apache.mahout.cf.taste.hadoop.item.recommenderjobtest@testaggregateandrecommendreducer", "_outcome": "pass"}, {"_tast_name": "org.apache.mahout.cf.taste.common.commontest@testnsiexception", "_outcome": "pass"}, {"_tast_name": "org.apache.mahout.ga.watchmaker.cd.tool.cdinfostooltest@testgatherinfos", "_outcome": "error"}, {"_tast_name": "org.apache.mahout.clustering.testclusterclassifier@testdmclusterclassification", "_outcome": "pass"}, {"_tast_name": "org.apache.mahout.math.stats.entropy.entropytest@testletters", "_outcome": "error"}, {"_tast_name": "org.apache.mahout.clustering.dirichlet.testdirichletclustering@testdirichletdmcluster100", "_outcome": "pass"}, {"_tast_name": "org.apache.mahout.clustering.dirichlet.testmapreduce@testdriveriterationsmr", "_outcome": "error"}, {"_tast_name": "org.apache.mahout.vectorizer.encoders.constantvalueencodertest@testaddtovector", "_outcome": "pass"}, {"_tast_name": "org.apache.mahout.cf.taste.impl.common.bitsettest@testclear", "_outcome": "pass"}, {"_tast_name": "org.apache.mahout.cf.taste.hadoop.similarity.item.itemsimilarityjobtest@testcompletejob", "_outcome": "error"}, {"_tast_name": "org.apache.mahout.cf.taste.impl.recommender.slopeone.slopeonerecommendertest@testrecommender", "_outcome": "pass"}, {"_tast_name": "org.apache.mahout.cf.taste.impl.recommender.knn.knnitembasedrecommendertest@testhowmany", "_outcome": "pass"}, {"_tast_name": "org.apache.mahout.cf.taste.impl.similarity.spearmancorrelationsimilaritytest@testfullcorrelation2", "_outcome": "pass"}, {"_tast_name": "org.apache.mahout.cf.taste.impl.similarity.spearmancorrelationsimilaritytest@testfullcorrelation1", "_outcome": "pass"}, {"_tast_name": "org.apache.mahout.math.vectortest@testhashcodeequivalence", "_outcome": "pass"}, {"_tast_name": "org.apache.mahout.cf.taste.impl.recommender.nullrescorertest@testuserrescorer", "_outcome": "pass"}, {"_tast_name": "org.apache.mahout.math.testmatrixview@testget", "_outcome": "pass"}, {"_tast_name": "org.apache.mahout.cf.taste.impl.similarity.tanimotocoefficientsimilaritytest@testitemssimilarities", "_outcome": "pass"}, {"_tast_name": "org.apache.mahout.math.jet.random.exponentialtest@testnextdouble", "_outcome": "pass"}, {"_tast_name": "org.apache.mahout.math.jet.stat.gammatest@testgamma", "_outcome": "pass"}, {"_tast_name": "org.apache.mahout.cf.taste.impl.recommender.randomrecommendertest@testrecommender", "_outcome": "pass"}, {"_tast_name": "org.apache.mahout.classifier.sequencelearning.hmm.hmmutilstest@testvalidatorlegal", "_outcome": "pass"}, {"_tast_name": "org.apache.mahout.cf.taste.impl.similarity.euclideandistancesimilaritytest@testfullitemcorrelation2", "_outcome": "pass"}, {"_tast_name": "org.apache.mahout.classifier.evaluation.auctest@testentropy", "_outcome": "pass"}, {"_tast_name": "org.apache.mahout.cf.taste.impl.similarity.euclideandistancesimilaritytest@testfullitemcorrelation1", "_outcome": "pass"}, {"_tast_name": "org.apache.mahout.clustering.dirichlet.testmapreduce@testmriterations", "_outcome": "pass"}, {"_tast_name": "org.apache.mahout.classifier.df.data.datatest@testcountlabel", "_outcome": "pass"}, {"_tast_name": "org.apache.mahout.clustering.testclusterinterface@testmscanopyasformatstringsparse", "_outcome": "pass"}, {"_tast_name": "org.apache.mahout.classifier.df.data.dataconvertertest@testconvert", "_outcome": "pass"}, {"_tast_name": "org.apache.mahout.cf.taste.impl.similarity.pearsoncorrelationsimilaritytest@testnoitemcorrelation1", "_outcome": "pass"}, {"_tast_name": "org.apache.mahout.cf.taste.impl.similarity.pearsoncorrelationsimilaritytest@testnoitemcorrelation2", "_outcome": "pass"}, {"_tast_name": "org.apache.mahout.cf.taste.impl.similarity.pearsoncorrelationsimilaritytest@testnoitemcorrelation3", "_outcome": "pass"}, {"_tast_name": "org.apache.mahout.ga.watchmaker.cd.tool.toolmappertest@testextractignoredattributes", "_outcome": "pass"}, {"_tast_name": "org.apache.mahout.cf.taste.hadoop.item.recommenderjobtest@testaggregateandrecommendreducerlimitnumberofrecommendations", "_outcome": "pass"}, {"_tast_name": "org.apache.mahout.cf.taste.impl.common.fastmaptest@testmaxsize", "_outcome": "pass"}, {"_tast_name": "org.apache.mahout.math.testvectorview@testassigndoublearray", "_outcome": "pass"}, {"_tast_name": "org.apache.mahout.math.stats.loglikelihoodtest@testentropy", "_outcome": "pass"}, {"_tast_name": "org.apache.mahout.cf.taste.impl.common.runningaverageandstddevtest@testfullbig", "_outcome": "pass"}, {"_tast_name": "org.apache.mahout.cf.taste.impl.common.fastmaptest@testputandget", "_outcome": "pass"}, {"_tast_name": "org.apache.mahout.classifier.confusionmatrixtest@testgetmatrix", "_outcome": "pass"}, {"_tast_name": "org.apache.mahout.vectorizer.sparsevectorsfromsequencefilestest@testcreatetermfrequencyvectorsnam", "_outcome": "error"}, {"_tast_name": "org.apache.mahout.cf.taste.impl.common.fastmaptest@testcontains", "_outcome": "pass"}, {"_tast_name": "org.apache.mahout.math.ssvd.sequentialbigsvdtest@testsingularvalues", "_outcome": "pass"}, {"_tast_name": "org.apache.mahout.clustering.kmeans.testkmeansclustering@testkmeansmapper", "_outcome": "pass"}, {"_tast_name": "org.apache.mahout.cf.taste.hadoop.item.recommenderjobtest@testitemfiltermapper", "_outcome": "pass"}, {"_tast_name": "org.apache.mahout.math.testmatrixview@testlabelbindingserialization", "_outcome": "pass"}, {"_tast_name": "org.apache.mahout.cf.taste.impl.common.runningaverageandstddevtest@testfull", "_outcome": "pass"}, {"_tast_name": "org.apache.mahout.cf.taste.impl.recommender.slopeone.memorydiffstoragetest@testupdateweighted", "_outcome": "pass"}, {"_tast_name": "org.apache.mahout.cf.taste.impl.model.genericuserpreferencearraytest@testsetvalue", "_outcome": "pass"}, {"_tast_name": "org.apache.mahout.classifier.sequencelearning.hmm.hmmalgorithmstest@testviterbialgorithm", "_outcome": "pass"}, {"_tast_name": "org.apache.mahout.cf.taste.impl.recommender.genericitembasedrecommendertest@testmostsimilartomultipleexcludeifnotsimilartoall", "_outcome": "pass"}, {"_tast_name": "org.apache.mahout.cf.taste.impl.common.fastbyidmaptest@testsizeempty", "_outcome": "pass"}, {"_tast_name": "org.apache.mahout.math.testmatrixview@testsetover", "_outcome": "pass"}, {"_tast_name": "org.apache.mahout.cf.taste.impl.common.cachetest@testlotsofgets", "_outcome": "pass"}, {"_tast_name": "org.apache.mahout.clustering.meanshift.testmeanshift@testcanopyeuclideanseqjobnoclustering", "_outcome": "pass"}, {"_tast_name": "org.apache.mahout.cf.taste.impl.similarity.tanimotocoefficientsimilaritytest@testnocorrelation", "_outcome": "pass"}, {"_tast_name": "org.apache.mahout.classifier.bayes.bayesfeaturemapreducetest@testminboth", "_outcome": "error"}, {"_tast_name": "org.apache.mahout.classifier.df.mapreduce.partial.treeidtest@testtreeid", "_outcome": "pass"}, {"_tast_name": "org.apache.mahout.classifier.df.data.datatest@testidenticaltrue", "_outcome": "pass"}, {"_tast_name": "org.apache.mahout.cf.taste.impl.recommender.genericitembasedrecommendertest@testbestrating", "_outcome": "pass"}, {"_tast_name": "org.apache.mahout.classifier.df.data.datatest@testrsplit", "_outcome": "pass"}, {"_tast_name": "org.apache.mahout.classifier.bayes.bayesclassifierselftest@testselftestcbayes", "_outcome": "error"}, {"_tast_name": "org.apache.mahout.cf.taste.impl.common.fastmaptest@testentryset", "_outcome": "pass"}, {"_tast_name": "org.apache.mahout.ga.watchmaker.cd.cdruletest@testoconditionnumerical", "_outcome": "pass"}, {"_tast_name": "org.apache.mahout.clustering.testgaussianaccumulators@testolaccumulatorresults", "_outcome": "pass"}, {"_tast_name": "org.apache.mahout.clustering.lda.cvb.testcvbmodeltrainer@testinmemorycvb0", "_outcome": "pass"}, {"_tast_name": "org.apache.mahout.ga.watchmaker.cd.cdcrossovertest@testmate2", "_outcome": "pass"}, {"_tast_name": "org.apache.mahout.cf.taste.hadoop.item.recommenderjobtest@testtovectorandprefreducerexceptionon2vectors", "_outcome": "pass"}, {"_tast_name": "org.apache.mahout.ga.watchmaker.cd.cdcrossovertest@testmate1", "_outcome": "pass"}, {"_tast_name": "org.apache.mahout.math.testmatrixview@testassignrowcardinality", "_outcome": "pass"}, {"_tast_name": "org.apache.mahout.ga.watchmaker.mahoutevaluatortest@teststoreloadpopulation", "_outcome": "pass"}, {"_tast_name": "org.apache.mahout.math.varinttest@testsignednegativeint", "_outcome": "pass"}, {"_tast_name": "org.apache.mahout.math.vectortest@testlognormalize", "_outcome": "pass"}, {"_tast_name": "org.apache.mahout.clustering.dirichlet.testmapreduce@testdriveriterationsseq", "_outcome": "pass"}, {"_tast_name": "org.apache.mahout.cf.taste.impl.similarity.loglikelihoodsimilaritytest@testcorrelation", "_outcome": "pass"}, {"_tast_name": "org.apache.mahout.math.testvectorview@testplusdouble", "_outcome": "pass"}, {"_tast_name": "org.apache.mahout.math.decomposer.lanczos.testlanczossolver@testeigenvaluecheck", "_outcome": "pass"}, {"_tast_name": "org.apache.mahout.cf.taste.impl.common.fastidsettest@testcontains", "_outcome": "pass"}, {"_tast_name": "org.apache.mahout.classifier.df.data.datatest@testmajoritylabel", "_outcome": "pass"}, {"_tast_name": "org.apache.mahout.classifier.df.split.optigsplittest@testcomputesplit", "_outcome": "pass"}, {"_tast_name": "org.apache.mahout.math.vectortest@testemptyaggregate1", "_outcome": "pass"}, {"_tast_name": "org.apache.mahout.cf.taste.impl.common.bitsettest@testclone", "_outcome": "pass"}, {"_tast_name": "org.apache.mahout.clustering.dirichlet.testmapreduce@testdriveriterationsmahalanobismr", "_outcome": "error"}, {"_tast_name": "org.apache.mahout.cf.taste.impl.model.genericitempreferencearraytest@testsetvalue", "_outcome": "pass"}, {"_tast_name": "org.apache.mahout.cf.taste.impl.common.fastidsettest@testrehash", "_outcome": "pass"}, {"_tast_name": "org.apache.mahout.vectorizer.sparsevectorsfromsequencefilestest@testcreatetermfrequencyvectorsseqnam", "_outcome": "error"}, {"_tast_name": "org.apache.mahout.cf.taste.impl.recommender.knn.knnitembasedrecommendertest@testestimatepref", "_outcome": "pass"}, {"_tast_name": "org.apache.mahout.cf.taste.impl.similarity.euclideandistancesimilaritytest@testfullcorrelation1", "_outcome": "pass"}, {"_tast_name": "org.apache.mahout.common.iterator.testsamplingiterator@testexactsizematch", "_outcome": "pass"}, {"_tast_name": "org.apache.mahout.cf.taste.impl.common.fastidsettest@testreservedvalues", "_outcome": "pass"}, {"_tast_name": "org.apache.mahout.cf.taste.impl.recommender.allunknownitemscandidateitemsstrategytest@teststrategy", "_outcome": "pass"}, {"_tast_name": "org.apache.mahout.cf.taste.impl.similarity.file.fileitemsimilaritytest@testfilenotfoundexceptionfornonexistingfile", "_outcome": "pass"}, {"_tast_name": "org.apache.mahout.cf.taste.impl.similarity.pearsoncorrelationsimilaritytest@testsimpleweighted", "_outcome": "pass"}, {"_tast_name": "org.apache.mahout.cf.taste.impl.model.file.filedatamodeltest@testgetnumusers", "_outcome": "pass"}, {"_tast_name": "org.apache.mahout.cf.taste.impl.recommender.genericitembasedrecommendertest@testmostsimilartomultiple", "_outcome": "pass"}, {"_tast_name": "org.apache.mahout.math.hadoop.similarity.testvectordistancesimilarityjob@testvectordistancemapper", "_outcome": "pass"}, {"_tast_name": "org.apache.mahout.math.testmatrixview@testsetquick", "_outcome": "pass"}, {"_tast_name": "org.apache.mahout.ga.watchmaker.mahoutevaluatortest@testevaluate", "_outcome": "error"}, {"_tast_name": "org.apache.mahout.clustering.fuzzykmeans.testfuzzykmeansclustering@testfuzzykmeansreducer", "_outcome": "pass"}, {"_tast_name": "org.apache.mahout.clustering.testgaussianaccumulators@testaccumulatorweightedresults", "_outcome": "pass"}, {"_tast_name": "org.apache.mahout.ga.watchmaker.cd.cdmutationtest@testmutate", "_outcome": "pass"}, {"_tast_name": "org.apache.mahout.math.jet.random.engine.mersennetwistertest@test10001", "_outcome": "pass"}, {"_tast_name": "org.apache.mahout.math.ssvd.sequentialoutofcoresvdtest@testleftvectors", "_outcome": "pass"}, {"_tast_name": "org.apache.mahout.cf.taste.impl.common.refreshhelpertest@testnocallable", "_outcome": "pass"}, {"_tast_name": "org.apache.mahout.math.solver.testconjugategradientsolver@testconjugategradientsolver", "_outcome": "pass"}, {"_tast_name": "org.apache.mahout.clustering.dirichlet.testdistributions@testrmultinom", "_outcome": "pass"}, {"_tast_name": "org.apache.mahout.cf.taste.impl.similarity.euclideandistancesimilaritytest@testrefresh", "_outcome": "pass"}, {"_tast_name": "org.apache.mahout.cf.taste.impl.model.genericuserpreferencearraytest@testsort", "_outcome": "pass"}, {"_tast_name": "org.apache.mahout.math.vectortest@testdensevector", "_outcome": "pass"}, {"_tast_name": "org.apache.mahout.clustering.canopy.testcanopycreation@testclusteringmanhattanmr", "_outcome": "error"}, {"_tast_name": "org.apache.mahout.cf.taste.impl.common.invertedrunningaveragetest@testandstddevunsupported3", "_outcome": "pass"}, {"_tast_name": "org.apache.mahout.driver.mahoutdrivertest@testmain", "_outcome": "pass"}, {"_tast_name": "org.apache.mahout.cf.taste.impl.common.invertedrunningaveragetest@testandstddevunsupported1", "_outcome": "pass"}, {"_tast_name": "org.apache.mahout.ga.watchmaker.cd.datalinetest@testset", "_outcome": "pass"}, {"_tast_name": "org.apache.mahout.cf.taste.impl.model.genericuserpreferencearraytest@testitemid", "_outcome": "pass"}, {"_tast_name": "org.apache.mahout.cf.taste.impl.common.fastmaptest@testrehash", "_outcome": "pass"}, {"_tast_name": "org.apache.mahout.classifier.df.data.datatest@testsubset", "_outcome": "pass"}, {"_tast_name": "org.apache.mahout.cf.taste.impl.recommender.genericitembasedrecommendertest@testrecommendedbecause", "_outcome": "pass"}, {"_tast_name": "org.apache.mahout.cf.taste.impl.common.fastmaptest@testremove", "_outcome": "pass"}, {"_tast_name": "org.apache.mahout.math.vectortest@testmax", "_outcome": "pass"}, {"_tast_name": "org.apache.mahout.classifier.sequencelearning.hmm.hmmutilstest@testtruncatemodel", "_outcome": "pass"}, {"_tast_name": "org.apache.mahout.common.randomutilstest@testnexttwinprime", "_outcome": "pass"}, {"_tast_name": "org.apache.mahout.clustering.dirichlet.testdistributions@testrchisq", "_outcome": "pass"}, {"_tast_name": "org.apache.mahout.cf.taste.impl.similarity.pearsoncorrelationsimilaritytest@testsimple", "_outcome": "pass"}, {"_tast_name": "org.apache.mahout.cf.taste.impl.common.runningaverageandstddevtest@teststddev", "_outcome": "pass"}, {"_tast_name": "org.apache.mahout.cf.taste.impl.common.longprimitivearrayiteratortest@testnext", "_outcome": "pass"}, {"_tast_name": "org.apache.mahout.math.testvectorview@testassignunaryfunction", "_outcome": "pass"}, {"_tast_name": "org.apache.mahout.classifier.df.data.dataloadertest@testgeneratedataset", "_outcome": "pass"}, {"_tast_name": "org.apache.mahout.cf.taste.impl.common.refreshhelpertest@testalreadyrefreshed", "_outcome": "pass"}, {"_tast_name": "org.apache.mahout.cf.taste.impl.common.runningaveragetest@testcopyconstructor", "_outcome": "pass"}, {"_tast_name": "org.apache.mahout.math.testvectorview@testassigndoublearraycardinality", "_outcome": "pass"}, {"_tast_name": "org.apache.mahout.cf.taste.common.commontest@testtasteexception", "_outcome": "pass"}, {"_tast_name": "org.apache.mahout.cf.taste.impl.model.file.filedatamodeltest@testexplicitrefreshaftercompletefileupdate", "_outcome": "pass"}, {"_tast_name": "org.apache.mahout.math.vectortest@testequivalent", "_outcome": "pass"}, {"_tast_name": "org.apache.mahout.cf.taste.impl.common.fastidsettest@testversushashset", "_outcome": "pass"}, {"_tast_name": "org.apache.mahout.math.testsingularvaluedecomposition@testmorerows", "_outcome": "pass"}, {"_tast_name": "org.apache.mahout.cf.taste.impl.transforms.zscoretest@testallsame", "_outcome": "pass"}, {"_tast_name": "org.apache.mahout.clustering.spectral.common.testaffinitymatrixinputjob@testaffinitymatrixinputreducer", "_outcome": "pass"}, {"_tast_name": "org.apache.mahout.math.jet.stat.probabilitytest@testnormalcdf", "_outcome": "pass"}, {"_tast_name": "org.apache.mahout.math.hadoop.similarity.cooccurrence.measures.vectorsimilaritymeasurestest@testpearsoncorrelationsimilarity", "_outcome": "pass"}, {"_tast_name": "org.apache.mahout.classifier.sequencelearning.hmm.hmmtrainertest@testviterbitraining", "_outcome": "pass"}, {"_tast_name": "org.apache.mahout.math.hadoop.stats.basicstatstest@teststddev", "_outcome": "error"}, {"_tast_name": "org.apache.mahout.clustering.canopy.testcanopycreation@testreferencemanhattan", "_outcome": "pass"}, {"_tast_name": "org.apache.mahout.cf.taste.hadoop.item.recommenderjobtest@testcompletejobboolean", "_outcome": "error"}, {"_tast_name": "org.apache.mahout.cf.taste.impl.recommender.genericuserbasedrecommendertest@testhowmany", "_outcome": "pass"}, {"_tast_name": "org.apache.mahout.math.vectortest@testemptyaggregate2", "_outcome": "pass"}, {"_tast_name": "org.apache.mahout.clustering.dirichlet.testdirichletclustering@testdirichletcluster100", "_outcome": "pass"}, {"_tast_name": "org.apache.mahout.math.hadoop.testdistributedrowmatrix@testtranspose", "_outcome": "error"}, {"_tast_name": "org.apache.mahout.math.testvectorview@testlike", "_outcome": "pass"}, {"_tast_name": "org.apache.mahout.math.jet.random.normaltest@testcdf", "_outcome": "pass"}, {"_tast_name": "org.apache.mahout.math.testmatrixview@testassignmatrix", "_outcome": "pass"}, {"_tast_name": "org.apache.mahout.clustering.kmeans.testkmeansclustering@testrunkmeansiterationconvergesinonerunwithgivendistancethreshold", "_outcome": "pass"}, {"_tast_name": "org.apache.mahout.cf.taste.impl.recommender.genericitembasedrecommendertest@testmostsimilartomultipledontexcludeifnotsimilartoall", "_outcome": "pass"}, {"_tast_name": "org.apache.mahout.classifier.df.node.nodetest@testreadleaf", "_outcome": "pass"}, {"_tast_name": "org.apache.mahout.common.intpairwritabletest@testwritable", "_outcome": "pass"}, {"_tast_name": "org.apache.mahout.cf.taste.impl.model.genericuserpreferencearraytest@testclone", "_outcome": "pass"}, {"_tast_name": "org.apache.mahout.math.stats.onlineauctest@testbinarycase", "_outcome": "pass"}, {"_tast_name": "org.apache.mahout.cf.taste.impl.model.file.fileidmigratortest@testnorefreshafterfileupdate", "_outcome": "pass"}, {"_tast_name": "org.apache.mahout.cf.taste.impl.common.fastidsettest@testiterator", "_outcome": "pass"}, {"_tast_name": "org.apache.mahout.vectorizer.encoders.wordlikevalueencodertest@teststaticweights", "_outcome": "pass"}, {"_tast_name": "org.apache.mahout.math.stats.onlineexponentialaveragetest@testrate", "_outcome": "pass"}, {"_tast_name": "org.apache.mahout.math.hadoop.stats.basicstatstest@teststddev2", "_outcome": "error"}, {"_tast_name": "org.apache.mahout.math.ssvd.sequentialbigsvdtest@testrightvectors", "_outcome": "pass"}, {"_tast_name": "org.apache.mahout.cf.taste.impl.similarity.genericitemsimilaritytest@testallsimilaritieswithindex", "_outcome": "pass"}, {"_tast_name": "org.apache.mahout.math.varinttest@testsignedpositivelong", "_outcome": "pass"}, {"_tast_name": "org.apache.mahout.math.hadoop.solver.testdistributedconjugategradientsolvercli@testsolver", "_outcome": "error"}, {"_tast_name": "org.apache.mahout.math.testmatrixview@testviewcolumnindexunder", "_outcome": "pass"}, {"_tast_name": "org.apache.mahout.cf.taste.impl.eval.rmsrecommenderevaluatortest@testevaluate", "_outcome": "pass"}, {"_tast_name": "org.apache.mahout.cf.taste.hadoop.item.touservectorsreducertest@testtousersreducerminpreferencesuserpasses", "_outcome": "pass"}, {"_tast_name": "org.apache.mahout.common.iterator.testsamplingiterator@testemptycase", "_outcome": "pass"}, {"_tast_name": "org.apache.mahout.common.randomutilstest@testisnotprime", "_outcome": "pass"}, {"_tast_name": "org.apache.mahout.cf.taste.impl.recommender.cachingrecommendertest@testrecommender", "_outcome": "pass"}, {"_tast_name": "org.apache.mahout.cf.taste.impl.recommender.treeclusteringrecommendertest@testestimatepref", "_outcome": "pass"}, {"_tast_name": "org.apache.mahout.classifier.df.data.datatest@testidenticalfalse", "_outcome": "pass"}, {"_tast_name": "org.apache.mahout.math.hadoop.stochasticsvd.ssvdprototypetest@testgivensqr", "_outcome": "pass"}, {"_tast_name": "org.apache.mahout.ga.watchmaker.cd.hadoop.cdmappertest@testmap", "_outcome": "pass"}, {"_tast_name": "org.apache.mahout.math.testmatrixview@testplusmatrix", "_outcome": "pass"}, {"_tast_name": "org.apache.mahout.vectorizer.encoders.textvalueencodertest@testasstring", "_outcome": "pass"}, {"_tast_name": "org.apache.mahout.math.vectortest@testaddto", "_outcome": "pass"}, {"_tast_name": "org.apache.mahout.cf.taste.hadoop.item.recommenderjobtest@testuservectorsplittermapperonlysomeprefsconsidered", "_outcome": "pass"}, {"_tast_name": "org.apache.mahout.classifier.sgd.passiveaggressivetest@testpassiveaggressive", "_outcome": "pass"}, {"_tast_name": "org.apache.mahout.math.testmatrixview@testviewrow", "_outcome": "pass"}, {"_tast_name": "org.apache.mahout.math.hadoop.similarity.cooccurrence.measures.vectorsimilaritymeasurestest@testcityblocksimilarity", "_outcome": "pass"}, {"_tast_name": "org.apache.mahout.cf.taste.impl.similarity.genericitemsimilaritytest@testallsimilaritieswithoutindex", "_outcome": "pass"}, {"_tast_name": "org.apache.mahout.math.testmatrixview@testtimesmatrixcardinality", "_outcome": "pass"}, {"_tast_name": "org.apache.mahout.math.hadoop.similarity.cooccurrence.measures.vectorsimilaritymeasurestest@testtanimotocoefficientsimilarity", "_outcome": "pass"}, {"_tast_name": "org.apache.mahout.math.testmatrixview@testassigndoublearrayarraycardinality", "_outcome": "pass"}, {"_tast_name": "org.apache.mahout.math.hadoop.testdistributedrowmatrix@testtransposejobconfbuilder", "_outcome": "pass"}, {"_tast_name": "org.apache.mahout.math.vectortest@testgetlengthsquared", "_outcome": "pass"}, {"_tast_name": "org.apache.mahout.clustering.dirichlet.testmapreduce@testdriveriterationsmahalanobisseq", "_outcome": "pass"}, {"_tast_name": "org.apache.mahout.cf.taste.impl.similarity.pearsoncorrelationsimilaritytest@testfullcorrelation1", "_outcome": "pass"}, {"_tast_name": "org.apache.mahout.clustering.testclusterclassifier@testgaussianclassifierserialization", "_outcome": "pass"}, {"_tast_name": "org.apache.mahout.cf.taste.impl.similarity.pearsoncorrelationsimilaritytest@testfullcorrelation2", "_outcome": "pass"}, {"_tast_name": "org.apache.mahout.math.testmatrixview@testgetindexunder", "_outcome": "pass"}, {"_tast_name": "org.apache.mahout.common.iterator.testsamplingiterator@testsample", "_outcome": "pass"}, {"_tast_name": "org.apache.mahout.clustering.canopy.testcanopycreation@testcanopymappermanhattan", "_outcome": "pass"}, {"_tast_name": "org.apache.mahout.clustering.meanshift.testmeanshift@testcanopyreducereuclidean", "_outcome": "pass"}, {"_tast_name": "org.apache.mahout.cf.taste.impl.recommender.slopeone.slopeonerecommendertest@testestimatepref", "_outcome": "pass"}, {"_tast_name": "org.apache.mahout.cf.taste.impl.model.booleanuserpreferencearraytest@testitemid", "_outcome": "pass"}, {"_tast_name": "org.apache.mahout.cf.taste.impl.similarity.euclideandistancesimilaritytest@testsimpleweighted", "_outcome": "pass"}, {"_tast_name": "org.apache.mahout.math.jet.random.engine.mersennetwistertest@testregression", "_outcome": "pass"}, {"_tast_name": "org.apache.mahout.cf.taste.impl.model.genericdatamodeltest@testserialization", "_outcome": "error"}, {"_tast_name": "org.apache.mahout.classifier.sgd.onlinelogisticregressiontest@testclassify", "_outcome": "pass"}, {"_tast_name": "org.apache.mahout.math.testvectorview@testassignvectorcardinality", "_outcome": "pass"}, {"_tast_name": "org.apache.mahout.math.testorderedintdoublemapping@testclone", "_outcome": "pass"}, {"_tast_name": "org.apache.mahout.math.jet.random.gammatest@testcdf", "_outcome": "pass"}, {"_tast_name": "org.apache.mahout.vectorizer.collocations.llr.gramtest@testequality", "_outcome": "pass"}, {"_tast_name": "org.apache.mahout.cf.taste.impl.similarity.pearsoncorrelationsimilaritytest@testnocorrelation1", "_outcome": "pass"}, {"_tast_name": "org.apache.mahout.cf.taste.impl.model.file.filedatamodeltest@testtostring", "_outcome": "pass"}, {"_tast_name": "org.apache.mahout.cf.taste.impl.similarity.pearsoncorrelationsimilaritytest@testnocorrelation3", "_outcome": "pass"}, {"_tast_name": "org.apache.mahout.cf.taste.impl.similarity.pearsoncorrelationsimilaritytest@testnocorrelation2", "_outcome": "pass"}, {"_tast_name": "org.apache.mahout.math.testmatrixview@testassignmatrixcardinality", "_outcome": "pass"}, {"_tast_name": "org.apache.mahout.ga.watchmaker.stfitnessevaluatortest@testevaluatesamepopulation", "_outcome": "pass"}, {"_tast_name": "org.apache.mahout.clustering.dirichlet.testmapreduce@testreducer", "_outcome": "pass"}, {"_tast_name": "org.apache.mahout.ga.watchmaker.cd.tool.toolmappertest@testextractattributes", "_outcome": "pass"}, {"_tast_name": "org.apache.mahout.math.stats.loglikelihoodtest@testfrequencycomparison", "_outcome": "pass"}, {"_tast_name": "org.apache.mahout.vectorizer.encoders.interactionvalueencodertest@testaddtovectorusesproductofweights", "_outcome": "pass"}, {"_tast_name": "org.apache.mahout.cf.taste.impl.common.samplinglongprimitiveiteratortest@testempty", "_outcome": "pass"}, {"_tast_name": "org.apache.mahout.math.hadoop.testdistributedrowmatrix@testmatrixmultiplactionjobconfbuilder", "_outcome": "pass"}, {"_tast_name": "org.apache.mahout.math.testmatrixview@testviewcolumn", "_outcome": "pass"}, {"_tast_name": "org.apache.mahout.cf.taste.impl.similarity.loglikelihoodsimilaritytest@testrefresh", "_outcome": "pass"}, {"_tast_name": "org.apache.mahout.clustering.testclusterinterface@testclusterasformatstringwithbindings", "_outcome": "pass"}, {"_tast_name": "org.apache.mahout.clustering.testclusterclassifier@testdmclassifierserialization", "_outcome": "pass"}, {"_tast_name": "org.apache.mahout.math.testmatrixview@testgetindexover", "_outcome": "pass"}, {"_tast_name": "org.apache.mahout.classifier.sequencelearning.hmm.hmmalgorithmstest@testlogscaledforwardalgorithm", "_outcome": "pass"}, {"_tast_name": "org.apache.mahout.cf.taste.impl.recommender.preferreditemsneighborhoodcandidateitemsstrategytest@teststrategy", "_outcome": "pass"}, {"_tast_name": "org.apache.mahout.math.stats.samplertest@testdiscretesampler", "_outcome": "pass"}, {"_tast_name": "org.apache.mahout.classifier.sgd.csvrecordfactorytest@testdictionaryorder", "_outcome": "pass"}, {"_tast_name": "org.apache.mahout.ep.evolutionaryprocesstest@testconverges", "_outcome": "pass"}, {"_tast_name": "org.apache.mahout.math.testvectorview@testminus", "_outcome": "pass"}, {"_tast_name": "org.apache.mahout.math.vectortest@testenumeration", "_outcome": "pass"}, {"_tast_name": "org.apache.mahout.math.murmurhashtest@testchangingkeylength", "_outcome": "pass"}, {"_tast_name": "org.apache.mahout.cf.taste.impl.common.fastmaptest@testgrow", "_outcome": "pass"}, {"_tast_name": "org.apache.mahout.math.testmatrixview@testsettinglabelbindings", "_outcome": "pass"}, {"_tast_name": "org.apache.mahout.clustering.canopy.testcanopycreation@testcanopyreducereuclidean", "_outcome": "pass"}, {"_tast_name": "org.apache.mahout.fpm.pfpgrowth.transactiontreetest@testtransactiontree", "_outcome": "pass"}, {"_tast_name": "org.apache.mahout.clustering.canopy.testcanopycreation@testclusteringeuclideanmr", "_outcome": "error"}, {"_tast_name": "org.apache.mahout.common.randomutilstest@testlongtoseed", "_outcome": "pass"}, {"_tast_name": "org.apache.mahout.clustering.testclusterinterface@testmscanopyasformatstring", "_outcome": "pass"}, {"_tast_name": "org.apache.mahout.cf.taste.hadoop.item.recommenderjobtest@testsimilaritymatrixrowwrappermapper", "_outcome": "pass"}, {"_tast_name": "org.apache.mahout.math.testmatrixview@testplusdouble", "_outcome": "pass"}, {"_tast_name": "org.apache.mahout.math.hadoop.similarity.cooccurrence.measures.vectorsimilaritymeasurestest@testloglikelihoodsimilarity", "_outcome": "pass"}, {"_tast_name": "org.apache.mahout.classifier.df.mapreduce.inmem.inmeminputformattest@testsplits", "_outcome": "pass"}, {"_tast_name": "org.apache.mahout.math.hadoop.testdistributedrowmatrix@testtimessquaredvectortempdirdeletion", "_outcome": "error"}, {"_tast_name": "org.apache.mahout.math.testvectorview@testassignbinaryfunction", "_outcome": "pass"}, {"_tast_name": "org.apache.mahout.cf.taste.impl.common.fastbyidmaptest@testmaxsize", "_outcome": "pass"}, {"_tast_name": "org.apache.mahout.clustering.spectral.eigencuts.testeigencutsaffinitycutsjob@testeigencutsaffinitycutsreducer", "_outcome": "pass"}, {"_tast_name": "org.apache.mahout.clustering.testclusterclassifier@testseqfileclusteriteratorkmeans", "_outcome": "pass"}, {"_tast_name": "org.apache.mahout.clustering.spectral.eigencuts.testeigencutssensitivityjob@testeigencutssensitivitymapper", "_outcome": "pass"}, {"_tast_name": "org.apache.mahout.cf.taste.impl.transforms.caseamplificationtest@testonevalue", "_outcome": "pass"}, {"_tast_name": "org.apache.mahout.classifier.naivebayes.complementarynaivebayesclassifiertest@testnaivebayes", "_outcome": "pass"}, {"_tast_name": "org.apache.mahout.math.varinttest@testsignedpositiveint", "_outcome": "pass"}, {"_tast_name": "org.apache.mahout.math.testmatrixview@testtranspose", "_outcome": "pass"}, {"_tast_name": "org.apache.mahout.classifier.df.mapreduce.inmem.inmeminputformattest@testrecordreader", "_outcome": "pass"}, {"_tast_name": "org.apache.mahout.classifier.bayes.bayesclassifiertest@test", "_outcome": "pass"}, {"_tast_name": "org.apache.mahout.clustering.spectral.common.testvectorcache@testall", "_outcome": "pass"}, {"_tast_name": "org.apache.mahout.math.testsingularvaluedecomposition@testuorthogonal", "_outcome": "pass"}, {"_tast_name": "org.apache.mahout.classifier.sequencelearning.hmm.hmmtrainertest@testscaledviterbitraining", "_outcome": "pass"}, {"_tast_name": "org.apache.mahout.ga.watchmaker.cd.tool.toolreducertest@testcreatedescriptionnominal", "_outcome": "pass"}, {"_tast_name": "org.apache.mahout.cf.taste.impl.common.fastidsettest@testremove", "_outcome": "pass"}, {"_tast_name": "org.apache.mahout.clustering.testclusterinterface@testclusterasformatstringsparsewithbindings", "_outcome": "pass"}, {"_tast_name": "org.apache.mahout.cf.taste.impl.common.samplinglongprimitiveiteratortest@testnext", "_outcome": "pass"}, {"_tast_name": "org.apache.mahout.cf.taste.impl.common.invertedrunningaveragetest@testaverage", "_outcome": "pass"}, {"_tast_name": "org.apache.mahout.math.testvectorview@testgetunder", "_outcome": "pass"}, {"_tast_name": "org.apache.mahout.math.jet.random.engine.mersennetwistertest@testdateconstructor", "_outcome": "pass"}, {"_tast_name": "org.apache.mahout.classifier.df.mapreduce.inmem.inmeminputsplittest@testwritable", "_outcome": "pass"}, {"_tast_name": "org.apache.mahout.math.vectortest@testvectorview", "_outcome": "pass"}, {"_tast_name": "org.apache.mahout.math.testmatrixview@testviewpartcardinality", "_outcome": "pass"}, {"_tast_name": "org.apache.mahout.cf.taste.hadoop.item.recommenderjobtest@testcompletejobwithfiltering", "_outcome": "error"}, {"_tast_name": "org.apache.mahout.math.hadoop.testdistributedrowmatrix@testtimessquaredjobconfbuilders", "_outcome": "pass"}, {"_tast_name": "org.apache.mahout.math.testvectorview@testzsum", "_outcome": "pass"}, {"_tast_name": "org.apache.mahout.common.distance.testminkowskimeasure@testmeasure", "_outcome": "pass"}, {"_tast_name": "org.apache.mahout.vectorizer.encoders.textvalueencodertest@testaddtovector", "_outcome": "pass"}, {"_tast_name": "org.apache.mahout.classifier.sequencelearning.hmm.hmmevaluatortest@testscaledmodellikelihood", "_outcome": "pass"}, {"_tast_name": "org.apache.mahout.math.choleskydecompositiontest@testrankdeficient", "_outcome": "pass"}, {"_tast_name": "org.apache.mahout.math.permutedvectorviewtest@testviewbasics", "_outcome": "pass"}, {"_tast_name": "org.apache.mahout.clustering.minhash.testminhashclustering@testmurmur3minhashmrjob", "_outcome": "error"}, {"_tast_name": "org.apache.mahout.math.testmatrixview@testassigncolumncardinality", "_outcome": "pass"}, {"_tast_name": "org.apache.mahout.cf.taste.impl.recommender.itemaveragerecommendertest@testrecommender", "_outcome": "pass"}, {"_tast_name": "org.apache.mahout.classifier.df.mapreduce.partial.partialbuildertest@testconfigure", "_outcome": "pass"}, {"_tast_name": "org.apache.mahout.vectorizer.encoders.textvalueencodertest@testluceneencoding", "_outcome": "pass"}, {"_tast_name": "org.apache.mahout.ga.watchmaker.cd.cdruletest@testwcondition", "_outcome": "pass"}, {"_tast_name": "org.apache.mahout.clustering.meanshift.testmeanshift@testcanopyeuclideanmrjobnoclustering", "_outcome": "error"}, {"_tast_name": "org.apache.mahout.common.distance.cosinedistancemeasuretest@testmeasure", "_outcome": "pass"}, {"_tast_name": "org.apache.mahout.vectorizer.collocations.llr.collocmappertest@testcollectngrams", "_outcome": "pass"}, {"_tast_name": "org.apache.mahout.cf.taste.impl.common.fastidsettest@testgrow", "_outcome": "pass"}, {"_tast_name": "org.apache.mahout.math.testvectorview@testtimesvectorcardinality", "_outcome": "pass"}, {"_tast_name": "org.apache.mahout.cf.taste.impl.common.cachetest@testmixedusage", "_outcome": "pass"}, {"_tast_name": "org.apache.mahout.math.hadoop.decomposer.testdistributedlanczossolvercli@testdistributedlanczossolverevjcli", "_outcome": "error"}, {"_tast_name": "org.apache.mahout.vectorizer.sparsevectorsfromsequencefilestest@testpruning", "_outcome": "error"}, {"_tast_name": "org.apache.mahout.classifier.bayes.bayesfeaturemapreducetest@testminsupport", "_outcome": "error"}, {"_tast_name": "org.apache.mahout.cf.taste.hadoop.item.recommenderjobtest@testcompletejob", "_outcome": "error"}, {"_tast_name": "org.apache.mahout.clustering.minhash.testminhashclustering@testmurmurminhashmrjob", "_outcome": "error"}, {"_tast_name": "org.apache.mahout.math.jet.random.normaltest@testtostring", "_outcome": "pass"}, {"_tast_name": "org.apache.mahout.math.stats.entropy.conditionalentropytest@testconditionalentropy", "_outcome": "error"}, {"_tast_name": "org.apache.mahout.vectorizer.highdfwordsprunertest@testhighdfwordspruning", "_outcome": "error"}, {"_tast_name": "org.apache.mahout.cf.taste.impl.common.fastbyidmaptest@testcontains", "_outcome": "pass"}, {"_tast_name": "org.apache.mahout.cf.taste.impl.recommender.slopeone.memorydiffstoragetest@testrecommendableidspockedunweighted", "_outcome": "pass"}, {"_tast_name": "org.apache.mahout.math.stats.onlinesummarizertest@testcount", "_outcome": "pass"}, {"_tast_name": "org.apache.mahout.cf.taste.impl.recommender.topitemstest@testtopusers", "_outcome": "pass"}, {"_tast_name": "org.apache.mahout.vectorizer.collocations.llr.gramtest@testconstructorsgetters", "_outcome": "pass"}, {"_tast_name": "org.apache.mahout.clustering.fuzzykmeans.testfuzzykmeansclustering@testreferenceimplementation", "_outcome": "pass"}, {"_tast_name": "org.apache.mahout.common.abstractjobtest@testoptions", "_outcome": "pass"}, {"_tast_name": "org.apache.mahout.math.testsingularvaluedecomposition@testconditionnumber", "_outcome": "pass"}, {"_tast_name": "org.apache.mahout.classifier.sequencelearning.hmm.hmmalgorithmstest@testlogscaledviterbialgorithm", "_outcome": "pass"}, {"_tast_name": "org.apache.mahout.math.testvectorview@testtimesvector", "_outcome": "pass"}, {"_tast_name": "org.apache.mahout.cf.taste.hadoop.similarity.item.itemsimilarityjobtest@testmostsimilaritemspairsmapper", "_outcome": "pass"}, {"_tast_name": "org.apache.mahout.cf.taste.impl.common.fastmaptest@testvalues", "_outcome": "pass"}, {"_tast_name": "org.apache.mahout.common.stringutilstest@teststringconversion", "_outcome": "error"}, {"_tast_name": "org.apache.mahout.clustering.testclusterinterface@testcanopyasformatstring", "_outcome": "pass"}, {"_tast_name": "org.apache.mahout.clustering.kmeans.testkmeansclustering@testkmeansreducer", "_outcome": "pass"}, {"_tast_name": "org.apache.mahout.math.jet.random.exponentialtest@testpdf", "_outcome": "pass"}, {"_tast_name": "org.apache.mahout.math.jet.random.gammatest@testnextdouble", "_outcome": "pass"}, {"_tast_name": "org.apache.mahout.math.testsingularvaluedecomposition@testdimensions", "_outcome": "pass"}, {"_tast_name": "org.apache.mahout.math.hadoop.stats.basicstatstest@testvar", "_outcome": "error"}, {"_tast_name": "org.apache.mahout.cf.taste.impl.recommender.genericuserbasedrecommendertest@testbestrating", "_outcome": "pass"}, {"_tast_name": "org.apache.mahout.cf.taste.impl.common.fastidsettest@testclear", "_outcome": "pass"}, {"_tast_name": "org.apache.mahout.vectorizer.encoders.continuousvalueencodertest@testasstring", "_outcome": "pass"}, {"_tast_name": "org.apache.mahout.cf.taste.impl.recommender.samplingcandidateitemsstrategytest@teststrategy", "_outcome": "pass"}, {"_tast_name": "org.apache.mahout.math.murmurhashtest@testchangingseed", "_outcome": "pass"}, {"_tast_name": "org.apache.mahout.math.testmatrixview@testsize", "_outcome": "pass"}, {"_tast_name": "org.apache.mahout.clustering.canopy.testcanopycreation@testcanopyreducert3t4configuration", "_outcome": "pass"}, {"_tast_name": "org.apache.mahout.cf.taste.impl.similarity.tanimotocoefficientsimilaritytest@testfullcorrelation2", "_outcome": "pass"}, {"_tast_name": "org.apache.mahout.math.testvectorview@testgetover", "_outcome": "pass"}, {"_tast_name": "org.apache.mahout.cf.taste.impl.similarity.tanimotocoefficientsimilaritytest@testfullcorrelation1", "_outcome": "pass"}, {"_tast_name": "org.apache.mahout.common.intpairwritabletest@testgetset", "_outcome": "pass"}, {"_tast_name": "org.apache.mahout.math.varinttest@testunsignedint", "_outcome": "pass"}, {"_tast_name": "org.apache.mahout.cf.taste.impl.recommender.knn.knnitembasedrecommendertest@testbestrating", "_outcome": "pass"}, {"_tast_name": "org.apache.mahout.clustering.canopy.testcanopycreation@testcanopymapperclusterfilter", "_outcome": "pass"}, {"_tast_name": "org.apache.mahout.common.iterator.testsamplingiterator@testabsurdsamplerate", "_outcome": "pass"}, {"_tast_name": "org.apache.mahout.vectorizer.collocations.llr.gramtest@testnull1", "_outcome": "pass"}, {"_tast_name": "org.apache.mahout.math.testmatrixview@testlike", "_outcome": "pass"}, {"_tast_name": "org.apache.mahout.clustering.testclusterclassifier@testgaussianclusterclassification", "_outcome": "pass"}, {"_tast_name": "org.apache.mahout.cf.taste.impl.recommender.genericuserbasedrecommendertest@testrescorer", "_outcome": "pass"}, {"_tast_name": "org.apache.mahout.math.testmatrixview@testviewpartindexover", "_outcome": "pass"}, {"_tast_name": "org.apache.mahout.clustering.lda.cvb.testcvbmodeltrainer@testrandomstructuredmodelviamr", "_outcome": "error"}, {"_tast_name": "org.apache.mahout.math.testmatrixview@testcopy", "_outcome": "pass"}, {"_tast_name": "org.apache.mahout.ga.watchmaker.cd.cdruletest@testoconditioncategorical", "_outcome": "pass"}, {"_tast_name": "org.apache.mahout.cf.taste.impl.similarity.euclideandistancesimilaritytest@testfullcorrelation1weighted", "_outcome": "pass"}, {"_tast_name": "org.apache.mahout.math.vectorwritabletest@testsequentialaccesssparsevectorwritable", "_outcome": "pass"}, {"_tast_name": "org.apache.mahout.vectorizer.sparsevectorsfromsequencefilestest@testpruningtf", "_outcome": "error"}, {"_tast_name": "org.apache.mahout.math.hadoop.similarity.cooccurrence.measures.vectorsimilaritymeasurestest@testeuclideandistancesimilarity", "_outcome": "pass"}, {"_tast_name": "org.apache.mahout.clustering.kmeans.testkmeansclustering@testreferenceimplementation", "_outcome": "pass"}, {"_tast_name": "org.apache.mahout.cf.taste.impl.model.booleanitempreferencearraytest@testclone", "_outcome": "pass"}, {"_tast_name": "org.apache.mahout.math.jet.random.exponentialtest@testcdf", "_outcome": "pass"}, {"_tast_name": "org.apache.mahout.math.hadoop.solver.testdistributedconjugategradientsolver@testsolver", "_outcome": "error"}, {"_tast_name": "org.apache.mahout.cf.taste.impl.common.longprimitivearrayiteratortest@testpeekskip", "_outcome": "pass"}, {"_tast_name": "org.apache.mahout.clustering.testclusterclassifier@testsoftclusterclassifierserialization", "_outcome": "pass"}, {"_tast_name": "org.apache.mahout.cf.taste.impl.common.refreshhelpertest@testcallable", "_outcome": "pass"}, {"_tast_name": "org.apache.mahout.math.testsingularvaluedecomposition@testaequalusvt", "_outcome": "pass"}, {"_tast_name": "org.apache.mahout.math.testmatrixview@testviewpart", "_outcome": "pass"}, {"_tast_name": "org.apache.mahout.math.testmatrixview@testcardinality", "_outcome": "pass"}, {"_tast_name": "org.apache.mahout.clustering.fuzzykmeans.testfuzzykmeansclustering@testfuzzykmeansmapper", "_outcome": "pass"}, {"_tast_name": "org.apache.mahout.clustering.canopy.testcanopycreation@testclusteringeuclideanseq", "_outcome": "pass"}, {"_tast_name": "org.apache.mahout.cf.taste.impl.similarity.file.fileitemsimilaritytest@testtostring", "_outcome": "pass"}, {"_tast_name": "org.apache.mahout.cf.taste.impl.recommender.knn.knnitembasedrecommendertest@testrescorer", "_outcome": "pass"}, {"_tast_name": "org.apache.mahout.cf.taste.impl.neighborhood.nearestnneighborhoodtest@testneighborhood", "_outcome": "pass"}, {"_tast_name": "org.apache.mahout.cf.taste.impl.common.longprimitivearrayiteratortest@testempty", "_outcome": "pass"}, {"_tast_name": "org.apache.mahout.vectorizer.encodedvectorsfromsequencefilestest@testcreatenamed", "_outcome": "error"}, {"_tast_name": "org.apache.mahout.cf.taste.impl.recommender.topitemstest@testtopitemitemalt", "_outcome": "pass"}, {"_tast_name": "org.apache.mahout.clustering.lda.testldainference@testldasparse", "_outcome": "pass"}, {"_tast_name": "org.apache.mahout.clustering.canopy.testcanopycreation@testclusteringmanhattanseq", "_outcome": "pass"}, {"_tast_name": "org.apache.mahout.math.testvectorview@testcardinality", "_outcome": "pass"}, {"_tast_name": "org.apache.mahout.cf.taste.impl.model.booleanitempreferencearraytest@testhaspref", "_outcome": "pass"}, {"_tast_name": "org.apache.mahout.cf.taste.impl.model.file.filedatamodeltest@testgetitems", "_outcome": "pass"}, {"_tast_name": "org.apache.mahout.cf.taste.impl.model.file.filedatamodeltest@testrefresh", "_outcome": "pass"}, {"_tast_name": "org.apache.mahout.clustering.canopy.testcanopycreation@testcanopyreducermanhattan", "_outcome": "pass"}, {"_tast_name": "org.apache.mahout.clustering.testclusterclassifier@testclusterclassifierserialization", "_outcome": "pass"}, {"_tast_name": "org.apache.mahout.cf.taste.impl.eval.averageabsolutedifferencerecommenderevaluatortest@testevaluate", "_outcome": "pass"}, {"_tast_name": "org.apache.mahout.common.distance.testchebyshevmeasure@testmeasure", "_outcome": "pass"}, {"_tast_name": "org.apache.mahout.math.decomposer.lanczos.testlanczossolver@testlanczossolversymmetric", "_outcome": "failure"}, {"_tast_name": "org.apache.mahout.cf.taste.hadoop.item.recommenderjobtest@testtoitemprefsmapperbooleandata", "_outcome": "pass"}, {"_tast_name": "org.apache.mahout.math.testvectorview@testtimesdouble", "_outcome": "pass"}, {"_tast_name": "org.apache.mahout.math.testvectorview@testdot", "_outcome": "pass"}, {"_tast_name": "org.apache.mahout.clustering.testgaussianaccumulators@testrsaccumulatorresults", "_outcome": "pass"}, {"_tast_name": "org.apache.mahout.cf.taste.impl.similarity.tanimotocoefficientsimilaritytest@testrefresh", "_outcome": "pass"}, {"_tast_name": "org.apache.mahout.clustering.kmeans.testkmeansclustering@testkmeanswithcanopyclusterinput", "_outcome": "error"}, {"_tast_name": "org.apache.mahout.cf.taste.impl.common.bitsettest@testbounds2", "_outcome": "pass"}, {"_tast_name": "org.apache.mahout.cf.taste.impl.model.booleanuserpreferencearraytest@testuserid", "_outcome": "pass"}, {"_tast_name": "org.apache.mahout.cf.taste.impl.model.genericuserpreferencearraytest@testuserid", "_outcome": "pass"}, {"_tast_name": "org.apache.mahout.cf.taste.impl.common.bitsettest@testbounds1", "_outcome": "pass"}, {"_tast_name": "org.apache.mahout.cf.taste.impl.model.file.filedatamodeltest@testfile", "_outcome": "pass"}, {"_tast_name": "org.apache.mahout.common.stringutilstest@testescape", "_outcome": "pass"}, {"_tast_name": "org.apache.mahout.math.testsingularvaluedecomposition@testvorthogonal", "_outcome": "pass"}, {"_tast_name": "org.apache.mahout.clustering.spectral.common.testmatrixdiagonalizejob@testmatrixdiagonalizereducer", "_outcome": "pass"}, {"_tast_name": "org.apache.mahout.clustering.testclusterinterface@testcanopyasformatstringwithbindings", "_outcome": "pass"}, {"_tast_name": "org.apache.mahout.cf.taste.impl.common.fastbyidmaptest@testrehash", "_outcome": "pass"}, {"_tast_name": "org.apache.mahout.math.ssvd.sequentialoutofcoresvdtest@testsingularvalues", "_outcome": "pass"}, {"_tast_name": "org.apache.mahout.clustering.meanshift.testmeanshift@testclustererreferenceimplementation", "_outcome": "pass"}, {"_tast_name": "org.apache.mahout.cf.taste.impl.similarity.tanimotocoefficientsimilaritytest@testcorrelation1", "_outcome": "pass"}, {"_tast_name": "org.apache.mahout.cf.taste.impl.similarity.tanimotocoefficientsimilaritytest@testcorrelation2", "_outcome": "pass"}, {"_tast_name": "org.apache.mahout.cf.taste.impl.similarity.genericitemsimilaritytest@testfromcorrelation", "_outcome": "pass"}, {"_tast_name": "org.apache.mahout.clustering.spectral.common.testmatrixdiagonalizejob@testmatrixdiagonalizemapper", "_outcome": "pass"}, {"_tast_name": "org.apache.mahout.cf.taste.impl.recommender.itemuseraveragerecommendertest@testrecommender", "_outcome": "pass"}, {"_tast_name": "org.apache.mahout.math.testmatrixview@testassigndouble", "_outcome": "pass"}, {"_tast_name": "org.apache.mahout.clustering.testclusterinterface@testmscanopyasformatstringwithbindings", "_outcome": "pass"}, {"_tast_name": "org.apache.mahout.cf.taste.impl.model.genericitempreferencearraytest@testitemid", "_outcome": "pass"}, {"_tast_name": "org.apache.mahout.cf.taste.impl.similarity.file.fileitemsimilaritytest@testfileitemitemsimilarityiterable", "_outcome": "pass"}, {"_tast_name": "org.apache.mahout.vectorizer.collocations.llr.gramtest@testnull2", "_outcome": "pass"}, {"_tast_name": "org.apache.mahout.classifier.df.tools.visualizertest@testpredicttrace", "_outcome": "pass"}, {"_tast_name": "org.apache.mahout.cf.taste.impl.similarity.tanimotocoefficientsimilaritytest@testreturnnandoublewhennosimilaritiesfortwoitems", "_outcome": "pass"}, {"_tast_name": "org.apache.mahout.math.solver.testconjugategradientsolver@testconditionedconjugategradientsolver", "_outcome": "pass"}, {"_tast_name": "org.apache.mahout.classifier.sgd.onlinelogisticregressiontest@testtrain", "_outcome": "pass"}, {"_tast_name": "org.apache.mahout.math.murmurhashtest@testhash64", "_outcome": "pass"}, {"_tast_name": "org.apache.mahout.cf.taste.impl.similarity.pearsoncorrelationsimilaritytest@testsimpleitemweighted", "_outcome": "pass"}, {"_tast_name": "org.apache.mahout.cf.taste.impl.common.weightedrunningaveragetest@testweighted", "_outcome": "pass"}, {"_tast_name": "org.apache.mahout.cf.taste.impl.recommender.treeclusteringrecommendertest@testbestrating", "_outcome": "pass"}, {"_tast_name": "org.apache.mahout.vectorizer.collocations.llr.collocmappertest@testcollectngramswithunigrams", "_outcome": "pass"}, {"_tast_name": "org.apache.mahout.classifier.discriminative.linearmodeltest@testadddelta", "_outcome": "pass"}, {"_tast_name": "org.apache.mahout.fpm.pfpgrowth.fpgrowthretaildatatest@testspecificcasefromretaildataminsup500", "_outcome": "pass"}, {"_tast_name": "org.apache.mahout.vectorizer.collocations.llr.gramkeygroupcomparatortest@testcomparator", "_outcome": "pass"}, {"_tast_name": "org.apache.mahout.fpm.pfpgrowth.fpgrowthsyntheticdatatest@testspecificcasesfromsynthdata", "_outcome": "pass"}, {"_tast_name": "org.apache.mahout.math.jet.stat.gammatest@testnegativeargforgamma", "_outcome": "pass"}, {"_tast_name": "org.apache.mahout.ga.watchmaker.cd.tool.toolcombinertest@testcreatedescriptionnumerical", "_outcome": "pass"}, {"_tast_name": "org.apache.mahout.math.testvectorview@testviewpart", "_outcome": "pass"}, {"_tast_name": "org.apache.mahout.math.jet.stat.probabilitytest@testloggamma", "_outcome": "pass"}, {"_tast_name": "org.apache.mahout.clustering.lda.testldainference@testldaeasy", "_outcome": "pass"}, {"_tast_name": "org.apache.mahout.classifier.discriminative.linearmodeltest@testclassify", "_outcome": "pass"}, {"_tast_name": "org.apache.mahout.math.testmatrixview@testassignrow", "_outcome": "pass"}, {"_tast_name": "org.apache.mahout.clustering.spectral.common.testvectorcache@testload", "_outcome": "pass"}, {"_tast_name": "org.apache.mahout.clustering.fuzzykmeans.testfuzzykmeansclustering@testfuzzykmeanscombiner", "_outcome": "pass"}, {"_tast_name": "org.apache.mahout.cf.taste.impl.common.fastidsettest@testcontainsandadd", "_outcome": "pass"}, {"_tast_name": "org.apache.mahout.classifier.df.mapreduce.partial.step1mappertest@testmapper", "_outcome": "pass"}, {"_tast_name": "org.apache.mahout.classifier.sequencelearning.hmm.hmmutilstest@testnormalizemodel", "_outcome": "pass"}, {"_tast_name": "org.apache.mahout.math.murmurhash3test@testcorrectvalues", "_outcome": "pass"}, {"_tast_name": "org.apache.mahout.ga.watchmaker.cd.hadoop.cdreducertest@testreduce", "_outcome": "pass"}, {"_tast_name": "org.apache.mahout.cf.taste.impl.recommender.genericitembasedrecommendertest@testhowmany", "_outcome": "pass"}, {"_tast_name": "org.apache.mahout.math.hadoop.similarity.testvectordistancesimilarityjob@testruninverted", "_outcome": "error"}, {"_tast_name": "org.apache.mahout.cf.taste.impl.similarity.genericitemsimilaritytest@testsimple", "_outcome": "pass"}, {"_tast_name": "org.apache.mahout.clustering.minhash.testminhashclustering@testlinearminhashmrjob", "_outcome": "error"}, {"_tast_name": "org.apache.mahout.cf.taste.impl.common.fastmaptest@testclear", "_outcome": "pass"}, {"_tast_name": "org.apache.mahout.math.testmatrixview@testminuscardinality", "_outcome": "pass"}, {"_tast_name": "org.apache.mahout.cf.taste.impl.recommender.genericuserbasedrecommendertest@testisolateduser", "_outcome": "pass"}, {"_tast_name": "org.apache.mahout.cf.taste.impl.common.samplinglongprimitiveiteratortest@testpeekskip", "_outcome": "pass"}, {"_tast_name": "org.apache.mahout.math.permutedvectorviewtest@testiterators", "_outcome": "pass"}, {"_tast_name": "org.apache.mahout.math.hadoop.similarity.testvectordistancesimilarityjob@testrun", "_outcome": "error"}, {"_tast_name": "org.apache.mahout.cf.taste.impl.recommender.slopeone.slopeonerecommendertest@testrescorer", "_outcome": "pass"}, {"_tast_name": "org.apache.mahout.cf.taste.hadoop.item.touservectorsreducertest@testtousersreducerminpreferencesuserignored", "_outcome": "pass"}, {"_tast_name": "org.apache.mahout.cf.taste.hadoop.item.recommenderjobtest@testtouservectorreducerwithbooleandata", "_outcome": "pass"}, {"_tast_name": "org.apache.mahout.clustering.topdown.postprocessor.clusteroutputpostprocessortest@testtopdownclustering", "_outcome": "pass"}, {"_tast_name": "org.apache.mahout.cf.taste.impl.similarity.euclideandistancesimilaritytest@testsimple", "_outcome": "pass"}, {"_tast_name": "org.apache.mahout.math.vectortest@testgetdistancesquared", "_outcome": "pass"}, {"_tast_name": "org.apache.mahout.clustering.fuzzykmeans.testfuzzykmeansclustering@testfuzzykmeansmrjob", "_outcome": "error"}, {"_tast_name": "org.apache.mahout.ga.watchmaker.cd.cdfitnesstest@testget", "_outcome": "pass"}, {"_tast_name": "org.apache.mahout.classifier.df.data.datatest@testidenticallabelfalse", "_outcome": "pass"}, {"_tast_name": "org.apache.mahout.math.solver.testconjugategradientsolver@testearlystop", "_outcome": "pass"}, {"_tast_name": "org.apache.mahout.clustering.testclusterclassifier@testclusteriteratordirichlet", "_outcome": "pass"}, {"_tast_name": "org.apache.mahout.classifier.sgd.adaptivelogisticregressiontest@testtrain", "_outcome": "pass"}, {"_tast_name": "org.apache.mahout.cf.taste.impl.model.booleanitempreferencearraytest@testsort", "_outcome": "pass"}, {"_tast_name": "org.apache.mahout.clustering.spectral.common.testvectormatrixmultiplicationjob@testvectormatrixmultiplicationmapper", "_outcome": "pass"}, {"_tast_name": "org.apache.mahout.math.murmurhashtest@testchangingkey", "_outcome": "pass"}, {"_tast_name": "org.apache.mahout.cf.taste.hadoop.item.recommenderjobtest@testtouservectorreducer", "_outcome": "pass"}, {"_tast_name": "org.apache.mahout.fpm.pfpgrowth.fpgrowth.frequentpatternmaxheaptest@testmapheap", "_outcome": "pass"}, {"_tast_name": "org.apache.mahout.math.testvectorview@testiterator", "_outcome": "pass"}, {"_tast_name": "org.apache.mahout.cf.taste.impl.model.file.fileidmigratortest@testrefreshafterfileupdate", "_outcome": "pass"}, {"_tast_name": "org.apache.mahout.cf.taste.impl.common.fastbyidmaptest@testversushashmap", "_outcome": "pass"}, {"_tast_name": "org.apache.mahout.cf.taste.hadoop.item.recommenderjobtest@testitemidindexmapper", "_outcome": "pass"}, {"_tast_name": "org.apache.mahout.math.testsingularvaluedecomposition@testhadamard", "_outcome": "pass"}, {"_tast_name": "org.apache.mahout.cf.taste.common.commontest@testnsuexception", "_outcome": "pass"}, {"_tast_name": "org.apache.mahout.math.hadoop.testdistributedrowmatrix@testmatrixtimesvector", "_outcome": "error"}, {"_tast_name": "org.apache.mahout.math.vectortest@testsparsevector", "_outcome": "pass"}, {"_tast_name": "org.apache.mahout.math.stats.loglikelihoodtest@testrootloglikelihood", "_outcome": "pass"}, {"_tast_name": "org.apache.mahout.cf.taste.hadoop.item.recommenderjobtest@testaggregateandrecommendreducerexcluderecommendationsbasedononeitem", "_outcome": "pass"}, {"_tast_name": "org.apache.mahout.math.varinttest@testsignedsize", "_outcome": "pass"}, {"_tast_name": "org.apache.mahout.classifier.df.data.dataloadertest@testgeneratedatasetfromfile", "_outcome": "pass"}, {"_tast_name": "org.apache.mahout.classifier.df.builder.infiniterecursiontest@testbuild", "_outcome": "pass"}, {"_tast_name": "org.apache.mahout.clustering.minhash.testminhashclustering@testpolynomialminhashmrjob", "_outcome": "error"}, {"_tast_name": "org.apache.mahout.vectorizer.collocations.llr.gramkeytest@testgramkeysort", "_outcome": "pass"}, {"_tast_name": "org.apache.mahout.vectorizer.encodedvectorsfromsequencefilestest@testcreateseq", "_outcome": "error"}, {"_tast_name": "org.apache.mahout.math.testmatrixview@testgetquick", "_outcome": "pass"}, {"_tast_name": "org.apache.mahout.cf.taste.impl.model.booleanuserpreferencearraytest@testhaspref", "_outcome": "pass"}, {"_tast_name": "org.apache.mahout.cf.taste.hadoop.item.recommenderjobtest@testuservectorsplittermapper", "_outcome": "pass"}, {"_tast_name": "org.apache.mahout.ga.watchmaker.cd.tool.toolcombinertest@testcreatedescriptionnominal", "_outcome": "pass"}, {"_tast_name": "org.apache.mahout.math.murmurhashtest@testforlotsofchange64", "_outcome": "pass"}, {"_tast_name": "org.apache.mahout.clustering.canopy.testcanopycreation@testclustermappermanhattan", "_outcome": "pass"}, {"_tast_name": "org.apache.mahout.cf.taste.impl.recommender.slopeone.memorydiffstoragetest@testremove", "_outcome": "pass"}, {"_tast_name": "org.apache.mahout.cf.taste.impl.recommender.slopeone.memorydiffstoragetest@testunrecommendableid", "_outcome": "pass"}, {"_tast_name": "org.apache.mahout.math.hadoop.decomposer.testdistributedlanczossolvercli@testdistributedlanczossolvercli", "_outcome": "error"}, {"_tast_name": "org.apache.mahout.vectorizer.dictionaryvectorizertest@testcreatetermfrequencyvectors", "_outcome": "error"}, {"_tast_name": "org.apache.mahout.classifier.df.mapreduce.inmem.inmeminputsplittest@testnullseed", "_outcome": "pass"}, {"_tast_name": "org.apache.mahout.math.testvectorview@testcopy", "_outcome": "pass"}, {"_tast_name": "org.apache.mahout.math.jet.random.gammatest@testpdf", "_outcome": "pass"}, {"_tast_name": "org.apache.mahout.classifier.df.data.datatest@testbagging", "_outcome": "pass"}, {"_tast_name": "org.apache.mahout.math.hadoop.similarity.testvectordistancesimilarityjob@testvectordistanceinvertedmapper", "_outcome": "pass"}, {"_tast_name": "org.apache.mahout.classifier.confusionmatrixtest@testbuild", "_outcome": "pass"}, {"_tast_name": "org.apache.mahout.math.testmatrixview@testzsum", "_outcome": "pass"}, {"_tast_name": "org.apache.mahout.vectorizer.encoders.continuousvalueencodertest@testaddtovector", "_outcome": "pass"}, {"_tast_name": "org.apache.mahout.clustering.meanshift.testmeanshift@testcanopyeuclideanseqjob", "_outcome": "pass"}, {"_tast_name": "org.apache.mahout.clustering.dirichlet.testdistributions@testrnorm", "_outcome": "pass"}, {"_tast_name": "org.apache.mahout.clustering.canopy.testcanopycreation@testclustermappereuclidean", "_outcome": "pass"}, {"_tast_name": "org.apache.mahout.cf.taste.impl.similarity.file.fileitemsimilaritytest@testnorefreshafterfileupdate", "_outcome": "pass"}, {"_tast_name": "org.apache.mahout.classifier.df.builder.defaulttreebuildertest@testrandomattributes", "_outcome": "pass"}, {"_tast_name": "org.apache.mahout.vectorizer.sparsevectorsfromsequencefilestest@testcreatetermfrequencyvectorsseq", "_outcome": "error"}, {"_tast_name": "org.apache.mahout.cf.taste.impl.recommender.slopeone.memorydiffstoragetest@testrecommendableidsvariedweighted", "_outcome": "pass"}, {"_tast_name": "org.apache.mahout.vectorizer.encoders.interactionvalueencodertest@testaddtovector", "_outcome": "pass"}, {"_tast_name": "org.apache.mahout.vectorizer.collocations.llr.collocreducertest@testreduce", "_outcome": "pass"}, {"_tast_name": "org.apache.mahout.math.testvectorview@testdividedouble", "_outcome": "pass"}, {"_tast_name": "org.apache.mahout.math.testvectorview@testdotcardinality", "_outcome": "pass"}, {"_tast_name": "org.apache.mahout.clustering.dirichlet.testdirichletclustering@testdirichletgaussiancluster100", "_outcome": "pass"}, {"_tast_name": "org.apache.mahout.cf.taste.impl.model.file.filedatamodeltest@testtranspose", "_outcome": "pass"}, {"_tast_name": "org.apache.mahout.math.testmatrixview@testtimesdouble", "_outcome": "pass"}, {"_tast_name": "org.apache.mahout.math.testmatrixview@testsetunder", "_outcome": "pass"}, {"_tast_name": "org.apache.mahout.clustering.canopy.testcanopycreation@testcanopyreducerclusterfilter", "_outcome": "pass"}, {"_tast_name": "org.apache.mahout.classifier.sequencelearning.hmm.hmmalgorithmstest@testforwardalgorithm", "_outcome": "pass"}, {"_tast_name": "org.apache.mahout.clustering.canopy.testcanopycreation@testcanopymappereuclidean", "_outcome": "pass"}, {"_tast_name": "org.apache.mahout.cf.taste.impl.similarity.file.fileitemsimilaritytest@testrefreshafterfileupdate", "_outcome": "pass"}, {"_tast_name": "org.apache.mahout.math.choleskydecompositiontest@test1", "_outcome": "pass"}, {"_tast_name": "org.apache.mahout.classifier.bayes.bayesfeaturemapreducetest@testmindf", "_outcome": "error"}, {"_tast_name": "org.apache.mahout.clustering.testgaussianaccumulators@testaccumulatornosamples", "_outcome": "pass"}, {"_tast_name": "org.apache.mahout.classifier.bayes.bayesfileformattertest@test", "_outcome": "pass"}, {"_tast_name": "org.apache.mahout.cf.taste.impl.common.fastbyidmaptest@testremove", "_outcome": "pass"}, {"_tast_name": "org.apache.mahout.clustering.kmeans.testkmeansclustering@testkmeansmrjob", "_outcome": "error"}, {"_tast_name": "org.apache.mahout.clustering.spectral.common.testunitvectorizerjob@testunitvectorizermapper", "_outcome": "pass"}, {"_tast_name": "org.apache.mahout.cf.taste.impl.recommender.slopeone.memorydiffstoragetest@testupdate", "_outcome": "pass"}, {"_tast_name": "org.apache.mahout.classifier.sequencelearning.hmm.hmmalgorithmstest@testlogscaledbackwardalgorithm", "_outcome": "pass"}, {"_tast_name": "org.apache.mahout.vectorizer.collocations.llr.gramkeypartitionertest@testpartition", "_outcome": "pass"}, {"_tast_name": "org.apache.mahout.cf.taste.impl.recommender.genericitembasedrecommendertest@testmostsimilar", "_outcome": "pass"}, {"_tast_name": "org.apache.mahout.vectorizer.collocations.llr.gramtest@testwritable", "_outcome": "pass"}, {"_tast_name": "org.apache.mahout.vectorizer.collocations.llr.gramtest@testsorting", "_outcome": "pass"}, {"_tast_name": "org.apache.mahout.vectorizer.encodedvectorsfromsequencefilestest@testcreateseqnamed", "_outcome": "error"}, {"_tast_name": "org.apache.mahout.classifier.df.mapreduce.partial.partialbuildertest@testprocessoutput", "_outcome": "pass"}, {"_tast_name": "org.apache.mahout.math.vectorwritabletest@testdensevectorwritable", "_outcome": "pass"}, {"_tast_name": "org.apache.mahout.math.stats.entropy.informationgainratiotest@testinformationgain", "_outcome": "error"}, {"_tast_name": "org.apache.mahout.vectorizer.dictionaryvectorizertest@testcreatetermfrequencyvectorsnam", "_outcome": "error"}, {"_tast_name": "org.apache.mahout.classifier.sequencelearning.hmm.hmmutilstest@testencodestatesequence", "_outcome": "pass"}, {"_tast_name": "org.apache.mahout.cf.taste.impl.recommender.treeclusteringrecommendertest@testnorecommendations", "_outcome": "pass"}, {"_tast_name": "org.apache.mahout.math.testvectorview@testset", "_outcome": "pass"}, {"_tast_name": "org.apache.mahout.clustering.meanshift.testmeanshift@testreferenceimplementation", "_outcome": "pass"}, {"_tast_name": "org.apache.mahout.cf.taste.impl.recommender.topitemstest@testtopitems", "_outcome": "pass"}, {"_tast_name": "org.apache.mahout.classifier.sequencelearning.hmm.hmmalgorithmstest@testbackwardalgorithm", "_outcome": "pass"}, {"_tast_name": "org.apache.mahout.math.matrixwritabletest@testdensematrixwritable", "_outcome": "pass"}, {"_tast_name": "org.apache.mahout.math.vectortest@testmin", "_outcome": "pass"}, {"_tast_name": "org.apache.mahout.clustering.spectral.common.testvectorcache@testsave", "_outcome": "pass"}, {"_tast_name": "org.apache.mahout.ga.watchmaker.cd.hadoop.datasetsplittest@testtrainingtestingsets", "_outcome": "pass"}, {"_tast_name": "org.apache.mahout.common.randomutilstest@testhashdouble", "_outcome": "pass"}, {"_tast_name": "org.apache.mahout.cf.taste.impl.similarity.pearsoncorrelationsimilaritytest@testinferrer", "_outcome": "pass"}, {"_tast_name": "org.apache.mahout.cf.taste.impl.recommender.genericuserbasedrecommendertest@testmostsimilar", "_outcome": "pass"}, {"_tast_name": "org.apache.mahout.vectorizer.highdfwordsprunertest@testhighdfwordspreserving", "_outcome": "error"}, {"_tast_name": "org.apache.mahout.clustering.testclusterclassifier@testclusterclassification", "_outcome": "pass"}, {"_tast_name": "org.apache.mahout.cf.taste.impl.recommender.topitemstest@testtopitemitem", "_outcome": "pass"}, {"_tast_name": "org.apache.mahout.common.iterator.countingiteratortest@testcount", "_outcome": "pass"}, {"_tast_name": "org.apache.mahout.math.stats.onlinesummarizertest@teststats", "_outcome": "pass"}, {"_tast_name": "org.apache.mahout.classifier.evaluation.auctest@testties", "_outcome": "pass"}, {"_tast_name": "org.apache.mahout.cf.taste.impl.common.fastbyidmaptest@testputandget", "_outcome": "pass"}, {"_tast_name": "org.apache.mahout.math.hadoop.testdistributedrowmatrix@testtimesvectortempdirdeletion", "_outcome": "error"}, {"_tast_name": "org.apache.mahout.math.testmatrixview@testtimesmatrix", "_outcome": "pass"}, {"_tast_name": "org.apache.mahout.math.jet.stat.gammatest@testbigx", "_outcome": "pass"}, {"_tast_name": "org.apache.mahout.math.testmatrixview@testlabelbindings", "_outcome": "pass"}, {"_tast_name": "org.apache.mahout.cf.taste.impl.recommender.slopeone.slopeonerecommendertest@testhowmany", "_outcome": "pass"}, {"_tast_name": "org.apache.mahout.cf.taste.hadoop.similarity.item.itemsimilarityjobtest@testmostsimilaritempairsreducer", "_outcome": "pass"}, {"_tast_name": "org.apache.mahout.math.testmatrixview@testminus", "_outcome": "pass"}, {"_tast_name": "org.apache.mahout.classifier.sequencelearning.hmm.hmmutilstest@testvalidatorillegelmatrixerror", "_outcome": "pass"}, {"_tast_name": "org.apache.mahout.cf.taste.impl.model.booleanitempreferencearraytest@testuserid", "_outcome": "pass"}, {"_tast_name": "org.apache.mahout.math.vectortest@testsparsevectorfulliteration", "_outcome": "pass"}, {"_tast_name": "org.apache.mahout.vectorizer.encodedvectorsfromsequencefilestest@testcreate", "_outcome": "error"}, {"_tast_name": "org.apache.mahout.cf.taste.impl.similarity.averagingpreferenceinferrertest@testinferrer", "_outcome": "pass"}, {"_tast_name": "org.apache.mahout.clustering.fuzzykmeans.testfuzzykmeansclustering@testclusterobservationsserialization", "_outcome": "pass"}, {"_tast_name": "org.apache.mahout.cf.taste.impl.model.file.filedatamodeltest@testemptyfile", "_outcome": "pass"}, {"_tast_name": "org.apache.mahout.classifier.df.node.nodetest@testparsenumerical", "_outcome": "pass"}, {"_tast_name": "org.apache.mahout.math.vectortest@testnormalize", "_outcome": "pass"}, {"_tast_name": "org.apache.mahout.common.randomutilstest@testsetseed", "_outcome": "pass"}, {"_tast_name": "org.apache.mahout.ga.watchmaker.cd.tool.descriptionutilstest@testextractnumericalrange", "_outcome": "pass"}, {"_tast_name": "org.apache.mahout.math.choleskydecompositiontest@test2", "_outcome": "pass"}, {"_tast_name": "org.apache.mahout.clustering.kmeans.testkmeansclustering@testkmeansseqjob", "_outcome": "pass"}, {"_tast_name": "org.apache.mahout.clustering.canopy.testcanopycreation@testcanopygeneuclideanmr", "_outcome": "error"}, {"_tast_name": "org.apache.mahout.cf.taste.impl.transforms.zscoretest@testexample", "_outcome": "pass"}, {"_tast_name": "org.apache.mahout.clustering.testclusterinterface@testmscanopyasformatstringsparsewithbindings", "_outcome": "pass"}, {"_tast_name": "org.apache.mahout.math.testmatrixview@testassigndoublearrayarray", "_outcome": "pass"}, {"_tast_name": "org.apache.mahout.clustering.fuzzykmeans.testfuzzykmeansclustering@testfuzzykmeansclustermapper", "_outcome": "pass"}, {"_tast_name": "org.apache.mahout.cf.taste.impl.similarity.spearmancorrelationsimilaritytest@testrefresh", "_outcome": "pass"}, {"_tast_name": "org.apache.mahout.math.testvectorview@testassignbinaryfunction2", "_outcome": "pass"}, {"_tast_name": "org.apache.mahout.cf.taste.impl.recommender.genericitembasedrecommendertest@testrescorer", "_outcome": "pass"}, {"_tast_name": "org.apache.mahout.classifier.sgd.gradientmachinetest@testgradientmachine", "_outcome": "pass"}, {"_tast_name": "org.apache.mahout.cf.taste.impl.recommender.genericitembasedrecommendertest@testestimatepref", "_outcome": "pass"}, {"_tast_name": "org.apache.mahout.classifier.naivebayes.naivebayesmodeltest@testrandommodelgeneration", "_outcome": "pass"}, {"_tast_name": "org.apache.mahout.math.hadoop.stochasticsvd.localssvdsolverdensetest@testssvdsolverdense", "_outcome": "error"}, {"_tast_name": "org.apache.mahout.math.decomposer.hebbian.testhebbiansolver@testhebbiansolver", "_outcome": "pass"}, {"_tast_name": "org.apache.mahout.common.abstractjobtest@testinputoutputpaths", "_outcome": "pass"}, {"_tast_name": "org.apache.mahout.math.varinttest@testunsignedlong", "_outcome": "pass"}, {"_tast_name": "org.apache.mahout.cf.taste.impl.model.genericitempreferencearraytest@testclone", "_outcome": "pass"}, {"_tast_name": "org.apache.mahout.ga.watchmaker.stfitnessevaluatortest@testevaluatedifferentpopulations", "_outcome": "pass"}, {"_tast_name": "org.apache.mahout.cf.taste.impl.similarity.euclideandistancesimilaritytest@testfullcorrelation2", "_outcome": "pass"}, {"_tast_name": "org.apache.mahout.cf.taste.impl.model.genericuserpreferencearraytest@testsortvalue", "_outcome": "pass"}, {"_tast_name": "org.apache.mahout.classifier.sequencelearning.hmm.hmmtrainertest@testbaumwelchtraining", "_outcome": "pass"}, {"_tast_name": "org.apache.mahout.classifier.df.data.datatest@testidenticallabeltrue", "_outcome": "pass"}, {"_tast_name": "org.apache.mahout.cf.taste.impl.similarity.pearsoncorrelationsimilaritytest@testnocorrelation1weighted", "_outcome": "pass"}, {"_tast_name": "org.apache.mahout.cf.taste.impl.common.fastidsettest@testsizeempty", "_outcome": "pass"}, {"_tast_name": "org.apache.mahout.math.jet.stat.probabilitytest@testbetacdf", "_outcome": "pass"}, {"_tast_name": "org.apache.mahout.clustering.testgaussianaccumulators@testaccumulatoronesample", "_outcome": "pass"}, {"_tast_name": "org.apache.mahout.ga.watchmaker.evalmappertest@testmap", "_outcome": "error"}, {"_tast_name": "org.apache.mahout.cf.taste.impl.common.bitsettest@testgetset", "_outcome": "pass"}, {"_tast_name": "org.apache.mahout.common.randomutilstest@testnextprime", "_outcome": "pass"}, {"_tast_name": "org.apache.mahout.vectorizer.collocations.llr.llrreducertest@testreduce", "_outcome": "pass"}, {"_tast_name": "org.apache.mahout.fpm.pfpgrowth.pfpgrowthretaildatatest@testretaildataminsup100", "_outcome": "error"}, {"_tast_name": "org.apache.mahout.cf.taste.impl.similarity.pearsoncorrelationsimilaritytest@testrefresh", "_outcome": "pass"}, {"_tast_name": "org.apache.mahout.classifier.df.builder.decisiontreebuildertest@testrandomattributes", "_outcome": "pass"}, {"_tast_name": "org.apache.mahout.fpm.pfpgrowth.fpgrowthsyntheticdatatest@testvswithsynthdata", "_outcome": "pass"}, {"_tast_name": "org.apache.mahout.math.testvectorview@testviewpartunder", "_outcome": "pass"}, {"_tast_name": "org.apache.mahout.clustering.testclusterinterface@testcanopyasformatstringsparse", "_outcome": "pass"}, {"_tast_name": "org.apache.mahout.math.testmatrixview@testviewcolumnindexover", "_outcome": "pass"}, {"_tast_name": "org.apache.mahout.math.murmurhashtest@testforlotsofchange32", "_outcome": "pass"}, {"_tast_name": "org.apache.mahout.math.testmatrixview@testviewrowindexover", "_outcome": "pass"}, {"_tast_name": "org.apache.mahout.common.randomutilstest@testhashfloat", "_outcome": "pass"}, {"_tast_name": "org.apache.mahout.vectorizer.encoders.wordlikevalueencodertest@testasstring", "_outcome": "pass"}, {"_tast_name": "org.apache.mahout.clustering.lda.testldainference@testldadense", "_outcome": "pass"}, {"_tast_name": "org.apache.mahout.common.iterator.testsamplingiterator@testsmallinput", "_outcome": "pass"}, {"_tast_name": "org.apache.mahout.math.testmatrixview@testplusmatrixcardinality", "_outcome": "pass"}, {"_tast_name": "org.apache.mahout.classifier.df.data.dataloadertest@testloaddatafromfile", "_outcome": "pass"}, {"_tast_name": "org.apache.mahout.math.testmatrixview@testassignunaryfunction", "_outcome": "pass"}, {"_tast_name": "org.apache.mahout.classifier.df.split.defaultigsplittest@testentropy", "_outcome": "pass"}, {"_tast_name": "org.apache.mahout.math.testmatrixview@testassigncolumn", "_outcome": "pass"}, {"_tast_name": "org.apache.mahout.classifier.df.data.datatest@testvalues", "_outcome": "pass"}, {"_tast_name": "org.apache.mahout.math.stats.onlineexponentialaveragetest@testaverage", "_outcome": "pass"}, {"_tast_name": "org.apache.mahout.classifier.discriminative.perceptrontrainertest@testupdate", "_outcome": "pass"}, {"_tast_name": "org.apache.mahout.clustering.dirichlet.testdistributions@testrbeta", "_outcome": "pass"}, {"_tast_name": "org.apache.mahout.common.iterator.countingiteratortest@testemptycase", "_outcome": "pass"}, {"_tast_name": "org.apache.mahout.ga.watchmaker.cd.fileinfosdatasettest@testranges", "_outcome": "pass"}, {"_tast_name": "org.apache.mahout.cf.taste.hadoop.item.recommenderjobtest@testuservectorsplittermapperuserexclusion", "_outcome": "pass"}, {"_tast_name": "org.apache.mahout.cf.taste.impl.similarity.pearsoncorrelationsimilaritytest@testfullcorrelation1weighted", "_outcome": "pass"}, {"_tast_name": "org.apache.mahout.clustering.spectral.eigencuts.testeigencutssensitivityjob@testeigencutssensitivityreducer", "_outcome": "pass"}, {"_tast_name": "org.apache.mahout.vectorizer.dictionaryvectorizertest@testcreatetermfrequencyvectorsseqnam", "_outcome": "error"}, {"_tast_name": "org.apache.mahout.ga.watchmaker.cd.tool.toolreducertest@testcreatedescriptionignored", "_outcome": "pass"}, {"_tast_name": "org.apache.mahout.classifier.sequencelearning.hmm.hmmutilstest@testdecodestatesequence", "_outcome": "pass"}, {"_tast_name": "org.apache.mahout.cf.taste.impl.recommender.topitemstest@testtopitemsrandom", "_outcome": "pass"}, {"_tast_name": "org.apache.mahout.cf.taste.impl.transforms.zscoretest@teststdev", "_outcome": "pass"}, {"_tast_name": "org.apache.mahout.cf.taste.impl.recommender.genericuserbasedrecommendertest@testrecommender", "_outcome": "pass"}, {"_tast_name": "org.apache.mahout.cf.taste.impl.recommender.slopeone.memorydiffstoragetest@testremovepref", "_outcome": "pass"}, {"_tast_name": "org.apache.mahout.cf.taste.impl.similarity.pearsoncorrelationsimilaritytest@testsimpleitem", "_outcome": "pass"}, {"_tast_name": "org.apache.mahout.cf.taste.impl.model.booleanuserpreferencearraytest@testsort", "_outcome": "pass"}, {"_tast_name": "org.apache.mahout.classifier.df.tools.visualizertest@testtreevisualize", "_outcome": "failure"}, {"_tast_name": "org.apache.mahout.cf.taste.impl.recommender.nullrescorertest@testitemrescorer", "_outcome": "pass"}, {"_tast_name": "org.apache.mahout.math.hadoop.similarity.cooccurrence.measures.vectorsimilaritymeasurestest@testcosinesimilarity", "_outcome": "pass"}, {"_tast_name": "org.apache.mahout.cf.taste.impl.model.genericitempreferencearraytest@testhaspref", "_outcome": "pass"}, {"_tast_name": "org.apache.mahout.classifier.sequencelearning.hmm.hmmutilstest@testvalidatordimensionerror", "_outcome": "pass"}, {"_tast_name": "org.apache.mahout.cf.taste.impl.transforms.caseamplificationtest@testrefresh", "_outcome": "pass"}, {"_tast_name": "org.apache.mahout.vectorizer.documentprocessortest@testtokenizedocuments", "_outcome": "error"}, {"_tast_name": "org.apache.mahout.math.vectorwritabletest@testnamedvectorwritable", "_outcome": "pass"}, {"_tast_name": "org.apache.mahout.vectorizer.encoders.interactionvalueencodertest@testaddtovectorwithtextvalueencoder", "_outcome": "pass"}, {"_tast_name": "org.apache.mahout.cf.taste.impl.similarity.spearmancorrelationsimilaritytest@testanticorrelation", "_outcome": "pass"}, {"_tast_name": "org.apache.mahout.cf.taste.impl.similarity.euclideandistancesimilaritytest@testnoitemcorrelation2", "_outcome": "pass"}, {"_tast_name": "org.apache.mahout.cf.taste.impl.similarity.euclideandistancesimilaritytest@testnoitemcorrelation3", "_outcome": "pass"}, {"_tast_name": "org.apache.mahout.cf.taste.impl.similarity.euclideandistancesimilaritytest@testnoitemcorrelation1", "_outcome": "pass"}, {"_tast_name": "org.apache.mahout.math.jet.random.normaltest@testsetstate", "_outcome": "pass"}, {"_tast_name": "org.apache.mahout.classifier.bayes.bayesfeaturemappertest@test", "_outcome": "error"}, {"_tast_name": "org.apache.mahout.classifier.sequencelearning.hmm.hmmmodeltest@testrandommodelgeneration", "_outcome": "pass"}, {"_tast_name": "org.apache.mahout.cf.taste.impl.recommender.genericitembasedrecommendertest@testrecommender", "_outcome": "pass"}, {"_tast_name": "org.apache.mahout.math.testorderedintdoublemapping@testgetset", "_outcome": "pass"}]